{"id":"5510ea66af1945352b1c986c","name":"Product","desc":"","descData":null,"closed":false,"idOrganization":null,"invited":false,"pinned":false,"starred":null,"url":"https://trello.com/b/VusqcRPc/product","prefs":{"permissionLevel":"public","voting":"disabled","comments":"members","invitations":"members","selfJoin":false,"cardCovers":true,"cardAging":"regular","calendarFeedEnabled":false,"background":"blue","backgroundColor":"#0079BF","backgroundImage":null,"backgroundImageScaled":null,"backgroundTile":false,"backgroundBrightness":"unknown","canBePublic":true,"canBeOrg":true,"canBePrivate":true,"canInvite":true},"invitations":[],"memberships":[{"id":"5510ea66af1945352b1c986d","idMember":"53c797959cd0710742a14dce","memberType":"admin","unconfirmed":false}],"shortLink":"VusqcRPc","subscribed":null,"labelNames":{"green":"","yellow":"","orange":"","red":"","purple":"","blue":"","sky":"","lime":"","pink":"","black":""},"powerUps":[],"dateLastActivity":"2015-06-06T19:07:38.546Z","dateLastView":null,"shortUrl":"https://trello.com/b/VusqcRPc","checklists":[],"labels":[{"id":"5510ea66664ce8ff30a32293","idBoard":"5510ea66af1945352b1c986c","name":"","color":"blue","uses":0},{"id":"5510ea66664ce8ff30a3228e","idBoard":"5510ea66af1945352b1c986c","name":"","color":"green","uses":0},{"id":"5510ea66664ce8ff30a32290","idBoard":"5510ea66af1945352b1c986c","name":"","color":"orange","uses":0},{"id":"5510ea66664ce8ff30a32292","idBoard":"5510ea66af1945352b1c986c","name":"","color":"purple","uses":0},{"id":"5510ea66664ce8ff30a32291","idBoard":"5510ea66af1945352b1c986c","name":"","color":"red","uses":0},{"id":"5510ea66664ce8ff30a3228f","idBoard":"5510ea66af1945352b1c986c","name":"","color":"yellow","uses":0}],"lists":[{"id":"5510ea7a72e8aec6ec62bdac","name":"作った","closed":false,"idBoard":"5510ea66af1945352b1c986c","pos":32767.5,"subscribed":null},{"id":"5510ea77b882b3677c740157","name":"作ってる","closed":false,"idBoard":"5510ea66af1945352b1c986c","pos":49151.25,"subscribed":null},{"id":"5510ea73de7581316ca2cad9","name":"作りたい","closed":false,"idBoard":"5510ea66af1945352b1c986c","pos":65535,"subscribed":null},{"id":"5510ec6028268c45e167bde6","name":"ネタ","closed":false,"idBoard":"5510ea66af1945352b1c986c","pos":262143,"subscribed":null},{"id":"552c7192acf369a608112162","name":"Done","closed":false,"idBoard":"5510ea66af1945352b1c986c","pos":327679,"subscribed":null}],"members":[{"id":"53c797959cd0710742a14dce","avatarHash":null,"bio":"","bioData":null,"confirmed":true,"fullName":"hash rock","idPremOrgsAdmin":null,"initials":"HR","memberType":"normal","products":[],"status":"disconnected","url":"https://trello.com/hashrock","username":"hashrock"}],"cards":[{"id":"554af9f2c279fd9fc6f2340e","badges":{"votes":0,"viewingMemberVoted":false,"subscribed":false,"fogbugz":"","checkItems":0,"checkItemsChecked":0,"comments":0,"attachments":1,"description":true,"due":null},"checkItemStates":[],"closed":false,"dateLastActivity":"2015-05-07T05:40:09.635Z","desc":"Markdownからカンバンに変換するライブラリ\n\nhttps://github.com/hashrock/kanbandown","descData":{"emoji":{}},"due":null,"email":null,"idBoard":"5510ea66af1945352b1c986c","idChecklists":[],"idList":"5510ea7a72e8aec6ec62bdac","idMembers":[],"idMembersVoted":[],"idShort":22,"idAttachmentCover":"554afa122bd688b4b7c1f983","manualCoverAttachment":false,"labels":[],"idLabels":[],"name":"kanbandown","pos":32767.5,"shortLink":"gxIwLfgw","shortUrl":"https://trello.com/c/gxIwLfgw","subscribed":null,"url":"https://trello.com/c/gxIwLfgw/22-kanbandown","attachments":[{"id":"554afa122bd688b4b7c1f983","bytes":346373,"date":"2015-05-07T05:37:22.248Z","edgeColor":"#f5f4f4","idMember":"53c797959cd0710742a14dce","isUpload":true,"mimeType":null,"name":"f6b25ee6-ec52-11e4-99ea-d074b2b9bcff.gif","previews":[{"width":70,"height":50,"url":"https://trello-attachments.s3.amazonaws.com/554af9f2c279fd9fc6f2340e/70x50/3084fa58738ecc03c8758a69274c26bb/f6b25ee6-ec52-11e4-99ea-d074b2b9bcff.gif.png","bytes":1903,"_id":"554afa132bd688b4b7c1f989","scaled":false},{"width":250,"height":150,"url":"https://trello-attachments.s3.amazonaws.com/554af9f2c279fd9fc6f2340e/250x150/c8c728f1ec5b7b22c83e3b5e020550ea/f6b25ee6-ec52-11e4-99ea-d074b2b9bcff.gif.png","bytes":17688,"_id":"554afa132bd688b4b7c1f988","scaled":false},{"width":150,"height":86,"url":"https://trello-attachments.s3.amazonaws.com/554af9f2c279fd9fc6f2340e/150x86/cb01aab0a60f0d6c84c6418b33a88026/f6b25ee6-ec52-11e4-99ea-d074b2b9bcff.gif.png","bytes":5296,"_id":"554afa132bd688b4b7c1f987","scaled":true},{"width":300,"height":172,"url":"https://trello-attachments.s3.amazonaws.com/554af9f2c279fd9fc6f2340e/300x172/dfdcdcfad964e857729ebf208f5cc1d0/f6b25ee6-ec52-11e4-99ea-d074b2b9bcff.gif.png","bytes":22629,"_id":"554afa132bd688b4b7c1f986","scaled":true},{"width":600,"height":343,"url":"https://trello-attachments.s3.amazonaws.com/554af9f2c279fd9fc6f2340e/600x343/da8b627c556f03d54405d9b8187c5292/f6b25ee6-ec52-11e4-99ea-d074b2b9bcff.gif.png","bytes":82921,"_id":"554afa132bd688b4b7c1f985","scaled":true},{"width":918,"height":525,"url":"https://trello-attachments.s3.amazonaws.com/554af9f2c279fd9fc6f2340e/918x525/598b63a03c056e5206a1400905664fe5/f6b25ee6-ec52-11e4-99ea-d074b2b9bcff.gif","bytes":346373,"_id":"554afa132bd688b4b7c1f984","scaled":true}],"url":"https://trello-attachments.s3.amazonaws.com/554af9f2c279fd9fc6f2340e/918x525/598b63a03c056e5206a1400905664fe5/f6b25ee6-ec52-11e4-99ea-d074b2b9bcff.gif"}]},{"id":"5510ea8f21854dede6dbcfea","badges":{"votes":0,"viewingMemberVoted":false,"subscribed":false,"fogbugz":"","checkItems":0,"checkItemsChecked":0,"comments":1,"attachments":1,"description":true,"due":null},"checkItemStates":[],"closed":false,"dateLastActivity":"2015-04-02T04:36:06.005Z","desc":"RPG風カンバンツール\n\n[DEMO](https://github.com/hashrock/taskquest)","descData":{"emoji":{}},"due":null,"email":null,"idBoard":"5510ea66af1945352b1c986c","idChecklists":[],"idList":"5510ea7a72e8aec6ec62bdac","idMembers":[],"idMembersVoted":[],"idShort":1,"idAttachmentCover":"5510ee186155825d18045c4a","manualCoverAttachment":false,"labels":[],"idLabels":[],"name":"taskquest","pos":65535,"shortLink":"R7jPrR4c","shortUrl":"https://trello.com/c/R7jPrR4c","subscribed":null,"url":"https://trello.com/c/R7jPrR4c/1-taskquest","attachments":[{"id":"5510ee186155825d18045c4a","bytes":56713,"date":"2015-03-24T04:54:48.767Z","edgeColor":"#1f3744","idMember":"53c797959cd0710742a14dce","isUpload":true,"mimeType":null,"name":"スクリーンショット 2015-03-24 13.54.29.png","previews":[{"width":70,"height":50,"url":"https://trello-attachments.s3.amazonaws.com/5510ea8f21854dede6dbcfea/70x50/292d3e2a1e85ed97e3a5773312947605/%E3%82%B9%E3%82%AF%E3%83%AA%E3%83%BC%E3%83%B3%E3%82%B7%E3%83%A7%E3%83%83%E3%83%88_2015-03-24_13.54.29.png","bytes":4933,"_id":"5510ee1a6155825d18045c50","scaled":false},{"width":250,"height":150,"url":"https://trello-attachments.s3.amazonaws.com/5510ea8f21854dede6dbcfea/250x150/6f68326c7c4dcb6977f162520e30a0f7/%E3%82%B9%E3%82%AF%E3%83%AA%E3%83%BC%E3%83%B3%E3%82%B7%E3%83%A7%E3%83%83%E3%83%88_2015-03-24_13.54.29.png","bytes":19927,"_id":"5510ee1a6155825d18045c4f","scaled":false},{"width":150,"height":100,"url":"https://trello-attachments.s3.amazonaws.com/5510ea8f21854dede6dbcfea/150x100/a5d73dffe69f8db8ed32a253d74c40ce/%E3%82%B9%E3%82%AF%E3%83%AA%E3%83%BC%E3%83%B3%E3%82%B7%E3%83%A7%E3%83%83%E3%83%88_2015-03-24_13.54.29.png","bytes":11913,"_id":"5510ee1a6155825d18045c4e","scaled":true},{"width":300,"height":201,"url":"https://trello-attachments.s3.amazonaws.com/5510ea8f21854dede6dbcfea/300x201/3c929b0e6e0e09571c2096fcb6e19d1e/%E3%82%B9%E3%82%AF%E3%83%AA%E3%83%BC%E3%83%B3%E3%82%B7%E3%83%A7%E3%83%83%E3%83%88_2015-03-24_13.54.29.png","bytes":28207,"_id":"5510ee1a6155825d18045c4d","scaled":true},{"width":600,"height":401,"url":"https://trello-attachments.s3.amazonaws.com/5510ea8f21854dede6dbcfea/600x401/ee2f88eaf47bcbf7a3025a6a6e21e230/%E3%82%B9%E3%82%AF%E3%83%AA%E3%83%BC%E3%83%B3%E3%82%B7%E3%83%A7%E3%83%83%E3%83%88_2015-03-24_13.54.29.png","bytes":61440,"_id":"5510ee1a6155825d18045c4c","scaled":true},{"width":1099,"height":735,"url":"https://trello-attachments.s3.amazonaws.com/5510ea8f21854dede6dbcfea/1099x735/a84ce67d604729c8f8d5f298a6cb9112/%E3%82%B9%E3%82%AF%E3%83%AA%E3%83%BC%E3%83%B3%E3%82%B7%E3%83%A7%E3%83%83%E3%83%88_2015-03-24_13.54.29.png","bytes":56713,"_id":"5510ee1a6155825d18045c4b","scaled":true}],"url":"https://trello-attachments.s3.amazonaws.com/5510ea8f21854dede6dbcfea/1099x735/a84ce67d604729c8f8d5f298a6cb9112/%E3%82%B9%E3%82%AF%E3%83%AA%E3%83%BC%E3%83%B3%E3%82%B7%E3%83%A7%E3%83%83%E3%83%88_2015-03-24_13.54.29.png"}]},{"id":"5510ebb8ae3a139d9e67ed4e","badges":{"votes":0,"viewingMemberVoted":false,"subscribed":false,"fogbugz":"","checkItems":0,"checkItemsChecked":0,"comments":1,"attachments":1,"description":true,"due":null},"checkItemStates":[],"closed":false,"dateLastActivity":"2015-04-02T04:35:43.264Z","desc":"小さなチーム内で情報共有するブログ\n\n[DEMO](https://github.com/hashrock/teamlog)","descData":{"emoji":{}},"due":null,"email":null,"idBoard":"5510ea66af1945352b1c986c","idChecklists":[],"idList":"5510ea7a72e8aec6ec62bdac","idMembers":[],"idMembersVoted":[],"idShort":3,"idAttachmentCover":"5510ebe215bbd2d63229ee2b","manualCoverAttachment":false,"labels":[],"idLabels":[],"name":"teamlog","pos":131071,"shortLink":"pRugcuUl","shortUrl":"https://trello.com/c/pRugcuUl","subscribed":null,"url":"https://trello.com/c/pRugcuUl/3-teamlog","attachments":[{"id":"5510ebe215bbd2d63229ee2b","bytes":23858,"date":"2015-03-24T04:45:22.731Z","edgeColor":"#fcfcfc","idMember":"53c797959cd0710742a14dce","isUpload":true,"mimeType":null,"name":"screenshot.png","previews":[{"width":70,"height":50,"url":"https://trello-attachments.s3.amazonaws.com/5510ebb8ae3a139d9e67ed4e/70x50/3d45b5029e664ffc2e55c28c485c3ff1/screenshot.png","bytes":2719,"_id":"5510ebe415bbd2d63229ee31","scaled":false},{"width":250,"height":150,"url":"https://trello-attachments.s3.amazonaws.com/5510ebb8ae3a139d9e67ed4e/250x150/18b94f33dcf62e4eb88f38e3bd9e14cf/screenshot.png","bytes":12987,"_id":"5510ebe415bbd2d63229ee30","scaled":false},{"width":150,"height":124,"url":"https://trello-attachments.s3.amazonaws.com/5510ebb8ae3a139d9e67ed4e/150x124/92d7867e8786a9cb89a69de198feb02b/screenshot.png","bytes":8489,"_id":"5510ebe415bbd2d63229ee2f","scaled":true},{"width":300,"height":248,"url":"https://trello-attachments.s3.amazonaws.com/5510ebb8ae3a139d9e67ed4e/300x248/7b8f06c0bd4287f65c74e09f06da3f1a/screenshot.png","bytes":23834,"_id":"5510ebe415bbd2d63229ee2e","scaled":true},{"width":600,"height":496,"url":"https://trello-attachments.s3.amazonaws.com/5510ebb8ae3a139d9e67ed4e/600x496/7f602f33727b9dbec928404e7fddaac9/screenshot.png","bytes":63601,"_id":"5510ebe415bbd2d63229ee2d","scaled":true},{"width":794,"height":656,"url":"https://trello-attachments.s3.amazonaws.com/5510ebb8ae3a139d9e67ed4e/794x656/f8cfc36ce39b80d66f8a1e5d5a9a1616/screenshot.png","bytes":23858,"_id":"5510ebe415bbd2d63229ee2c","scaled":true}],"url":"https://trello-attachments.s3.amazonaws.com/5510ebb8ae3a139d9e67ed4e/794x656/f8cfc36ce39b80d66f8a1e5d5a9a1616/screenshot.png"}]},{"id":"551ca6e36ab1822cb7820e9e","badges":{"votes":0,"viewingMemberVoted":false,"subscribed":false,"fogbugz":"","checkItems":0,"checkItemsChecked":0,"comments":0,"attachments":1,"description":true,"due":null},"checkItemStates":[],"closed":false,"dateLastActivity":"2015-04-02T04:37:13.562Z","desc":"npm script検索ツール\n\n[Github](https://github.com/sushicorp/sushipm)","descData":{"emoji":{}},"due":null,"email":null,"idBoard":"5510ea66af1945352b1c986c","idChecklists":[],"idList":"5510ea7a72e8aec6ec62bdac","idMembers":[],"idMembersVoted":[],"idShort":19,"idAttachmentCover":"551ca6edb94e922c28b3022a","manualCoverAttachment":false,"labels":[],"idLabels":[],"name":"sushipm","pos":196607,"shortLink":"sMeRPRU3","shortUrl":"https://trello.com/c/sMeRPRU3","subscribed":null,"url":"https://trello.com/c/sMeRPRU3/19-sushipm","attachments":[{"id":"551ca6edb94e922c28b3022a","bytes":146851,"date":"2015-04-02T02:18:21.887Z","edgeColor":"#042b34","idMember":"53c797959cd0710742a14dce","isUpload":true,"mimeType":null,"name":"8defc33e-d4b6-11e4-9507-4569c91960be.gif","previews":[{"width":70,"height":50,"url":"https://trello-attachments.s3.amazonaws.com/551ca6e36ab1822cb7820e9e/70x50/1076377acd7726c48a5bd5d5f4adc2ca/8defc33e-d4b6-11e4-9507-4569c91960be.gif.png","bytes":481,"_id":"551ca6efb94e922c28b3022f","scaled":false},{"width":250,"height":150,"url":"https://trello-attachments.s3.amazonaws.com/551ca6e36ab1822cb7820e9e/250x150/c1a91fce6e85805233f02f92c1d65a31/8defc33e-d4b6-11e4-9507-4569c91960be.gif.png","bytes":1533,"_id":"551ca6efb94e922c28b3022e","scaled":false},{"width":150,"height":112,"url":"https://trello-attachments.s3.amazonaws.com/551ca6e36ab1822cb7820e9e/150x112/21d33eda9b8857a90b65d8b5f12ed4b5/8defc33e-d4b6-11e4-9507-4569c91960be.gif.png","bytes":840,"_id":"551ca6efb94e922c28b3022d","scaled":true},{"width":300,"height":224,"url":"https://trello-attachments.s3.amazonaws.com/551ca6e36ab1822cb7820e9e/300x224/6b0c083f65e2f416adb7df4ffa6723f0/8defc33e-d4b6-11e4-9507-4569c91960be.gif.png","bytes":2106,"_id":"551ca6efb94e922c28b3022c","scaled":true},{"width":565,"height":421,"url":"https://trello-attachments.s3.amazonaws.com/551ca6e36ab1822cb7820e9e/565x421/5eb0c480bd6cd8dd2d7c0492500366f7/8defc33e-d4b6-11e4-9507-4569c91960be.gif","bytes":146851,"_id":"551ca6efb94e922c28b3022b","scaled":true}],"url":"https://trello-attachments.s3.amazonaws.com/551ca6e36ab1822cb7820e9e/565x421/5eb0c480bd6cd8dd2d7c0492500366f7/8defc33e-d4b6-11e4-9507-4569c91960be.gif"}]},{"id":"5510eea93d17d51bff963283","badges":{"votes":0,"viewingMemberVoted":false,"subscribed":false,"fogbugz":"","checkItems":0,"checkItemsChecked":0,"comments":1,"attachments":1,"description":true,"due":null},"checkItemStates":[],"closed":false,"dateLastActivity":"2015-03-24T12:10:47.387Z","desc":"テキストからガントチャートに変換するやつ","descData":{"emoji":{}},"due":null,"email":null,"idBoard":"5510ea66af1945352b1c986c","idChecklists":[],"idList":"5510ea77b882b3677c740157","idMembers":[],"idMembersVoted":[],"idShort":12,"idAttachmentCover":"5511404f4ab630ecd8b63ab8","manualCoverAttachment":false,"labels":[],"idLabels":[],"name":"Text2Gantt","pos":65535,"shortLink":"rYefpllB","shortUrl":"https://trello.com/c/rYefpllB","subscribed":null,"url":"https://trello.com/c/rYefpllB/12-text2gantt","attachments":[{"id":"5511404f4ab630ecd8b63ab8","bytes":54715,"date":"2015-03-24T10:45:35.072Z","edgeColor":null,"idMember":"53c797959cd0710742a14dce","isUpload":true,"mimeType":null,"name":"gantttext.png","previews":[{"width":70,"height":50,"url":"https://trello-attachments.s3.amazonaws.com/5510eea93d17d51bff963283/70x50/2eb5bd65a78242419b86f3738fb0f0dd/gantttext.png","bytes":2549,"_id":"551140514ab630ecd8b63abe","scaled":false},{"width":250,"height":150,"url":"https://trello-attachments.s3.amazonaws.com/5510eea93d17d51bff963283/250x150/7e78992f01fcdb1408e14f40c20aca8c/gantttext.png","bytes":9593,"_id":"551140514ab630ecd8b63abd","scaled":false},{"width":150,"height":104,"url":"https://trello-attachments.s3.amazonaws.com/5510eea93d17d51bff963283/150x104/a65067d801d903676954ffdcba393b03/gantttext.png","bytes":6652,"_id":"551140514ab630ecd8b63abc","scaled":true},{"width":300,"height":209,"url":"https://trello-attachments.s3.amazonaws.com/5510eea93d17d51bff963283/300x209/4e1998d678e9396fdc3d8f48f6f0f46b/gantttext.png","bytes":16247,"_id":"551140514ab630ecd8b63abb","scaled":true},{"width":600,"height":418,"url":"https://trello-attachments.s3.amazonaws.com/5510eea93d17d51bff963283/600x418/d4d1761975d4e3fdd0c6cf4640492101/gantttext.png","bytes":42042,"_id":"551140514ab630ecd8b63aba","scaled":true},{"width":1000,"height":696,"url":"https://trello-attachments.s3.amazonaws.com/5510eea93d17d51bff963283/1000x696/e9e0abbe5d8950b2d9f6b2531ef19566/gantttext.png","bytes":54715,"_id":"551140514ab630ecd8b63ab9","scaled":true}],"url":"https://trello-attachments.s3.amazonaws.com/5510eea93d17d51bff963283/1000x696/e9e0abbe5d8950b2d9f6b2531ef19566/gantttext.png"}]},{"id":"55123b647ed28b7bccbba95e","badges":{"votes":0,"viewingMemberVoted":false,"subscribed":false,"fogbugz":"","checkItems":0,"checkItemsChecked":0,"comments":3,"attachments":0,"description":false,"due":null},"checkItemStates":[],"closed":false,"dateLastActivity":"2015-05-07T08:47:24.247Z","desc":"","descData":null,"due":null,"email":null,"idBoard":"5510ea66af1945352b1c986c","idChecklists":[],"idList":"5510ea77b882b3677c740157","idMembers":[],"idMembersVoted":[],"idShort":18,"idAttachmentCover":null,"manualCoverAttachment":false,"labels":[],"idLabels":[],"name":"ライトウェイトなカンバンツール","pos":524287,"shortLink":"ZhPysPZq","shortUrl":"https://trello.com/c/ZhPysPZq","subscribed":null,"url":"https://trello.com/c/ZhPysPZq/18--","attachments":[]},{"id":"554afb35fe40cfba66515192","badges":{"votes":0,"viewingMemberVoted":false,"subscribed":false,"fogbugz":"","checkItems":0,"checkItemsChecked":0,"comments":0,"attachments":0,"description":false,"due":null},"checkItemStates":[],"closed":false,"dateLastActivity":"2015-06-06T19:04:56.628Z","desc":"","descData":null,"due":null,"email":null,"idBoard":"5510ea66af1945352b1c986c","idChecklists":[],"idList":"5510ea77b882b3677c740157","idMembers":[],"idMembersVoted":[],"idShort":26,"idAttachmentCover":null,"manualCoverAttachment":false,"labels":[],"idLabels":[],"name":"テスト項目書をExcelで書かなくて済むツール","pos":557055,"shortLink":"ulWZm2CN","shortUrl":"https://trello.com/c/ulWZm2CN","subscribed":null,"url":"https://trello.com/c/ulWZm2CN/26-excel","attachments":[]},{"id":"5510eea03d17d51bff96327c","badges":{"votes":0,"viewingMemberVoted":false,"subscribed":false,"fogbugz":"","checkItems":0,"checkItemsChecked":0,"comments":1,"attachments":0,"description":false,"due":null},"checkItemStates":[],"closed":false,"dateLastActivity":"2015-06-06T18:57:21.920Z","desc":"","descData":null,"due":null,"email":null,"idBoard":"5510ea66af1945352b1c986c","idChecklists":[],"idList":"5510ea77b882b3677c740157","idMembers":[],"idMembersVoted":[],"idShort":11,"idAttachmentCover":null,"manualCoverAttachment":false,"labels":[],"idLabels":[],"name":"かんたんGIFエディタ","pos":589823,"shortLink":"3a5beVlC","shortUrl":"https://trello.com/c/3a5beVlC","subscribed":null,"url":"https://trello.com/c/3a5beVlC/11-gif","attachments":[]},{"id":"5548c8772f9163a228decda4","badges":{"votes":0,"viewingMemberVoted":false,"subscribed":false,"fogbugz":"","checkItems":0,"checkItemsChecked":0,"comments":0,"attachments":0,"description":false,"due":null},"checkItemStates":[],"closed":false,"dateLastActivity":"2015-06-06T19:07:38.546Z","desc":"","descData":null,"due":null,"email":null,"idBoard":"5510ea66af1945352b1c986c","idChecklists":[],"idList":"5510ea77b882b3677c740157","idMembers":[],"idMembersVoted":[],"idShort":21,"idAttachmentCover":null,"manualCoverAttachment":false,"labels":[],"idLabels":[],"name":"ビルドごとに、撮影したgifをアップロードする場所","pos":655359,"shortLink":"Jhr5wRzh","shortUrl":"https://trello.com/c/Jhr5wRzh","subscribed":null,"url":"https://trello.com/c/Jhr5wRzh/21-gif","attachments":[]},{"id":"5510ee56ee3048887cf5faec","badges":{"votes":0,"viewingMemberVoted":false,"subscribed":false,"fogbugz":"","checkItems":0,"checkItemsChecked":0,"comments":0,"attachments":0,"description":false,"due":null},"checkItemStates":[],"closed":false,"dateLastActivity":"2015-03-24T04:55:50.518Z","desc":"","descData":null,"due":null,"email":null,"idBoard":"5510ea66af1945352b1c986c","idChecklists":[],"idList":"5510ea73de7581316ca2cad9","idMembers":[],"idMembersVoted":[],"idShort":10,"idAttachmentCover":null,"manualCoverAttachment":false,"labels":[],"idLabels":[],"name":"マルチプレイ型RPGツクールみたいなの","pos":131071,"shortLink":"5GkuKBzM","shortUrl":"https://trello.com/c/5GkuKBzM","subscribed":null,"url":"https://trello.com/c/5GkuKBzM/10-rpg","attachments":[]},{"id":"5510f1128f20837b9e199913","badges":{"votes":0,"viewingMemberVoted":false,"subscribed":false,"fogbugz":"","checkItems":0,"checkItemsChecked":0,"comments":0,"attachments":0,"description":false,"due":null},"checkItemStates":[],"closed":false,"dateLastActivity":"2015-03-24T05:07:30.790Z","desc":"","descData":null,"due":null,"email":null,"idBoard":"5510ea66af1945352b1c986c","idChecklists":[],"idList":"5510ea73de7581316ca2cad9","idMembers":[],"idMembersVoted":[],"idShort":13,"idAttachmentCover":null,"manualCoverAttachment":false,"labels":[],"idLabels":[],"name":"プロトタイピング向けライブラリ＆サービスのまとめ","pos":262143,"shortLink":"zizl5aPg","shortUrl":"https://trello.com/c/zizl5aPg","subscribed":null,"url":"https://trello.com/c/zizl5aPg/13--","attachments":[]},{"id":"5510f15a0c8bb992906a10bd","badges":{"votes":0,"viewingMemberVoted":false,"subscribed":false,"fogbugz":"","checkItems":0,"checkItemsChecked":0,"comments":0,"attachments":0,"description":false,"due":null},"checkItemStates":[],"closed":false,"dateLastActivity":"2015-03-24T05:08:42.344Z","desc":"","descData":null,"due":null,"email":null,"idBoard":"5510ea66af1945352b1c986c","idChecklists":[],"idList":"5510ea73de7581316ca2cad9","idMembers":[],"idMembersVoted":[],"idShort":14,"idAttachmentCover":null,"manualCoverAttachment":false,"labels":[],"idLabels":[],"name":"HandsonTable編集すると、JSONを公開してくれるサイト","pos":327679,"shortLink":"lLtgXnU7","shortUrl":"https://trello.com/c/lLtgXnU7","subscribed":null,"url":"https://trello.com/c/lLtgXnU7/14-handsontable-json","attachments":[]},{"id":"552ea92bfe0c77280b4d3d81","badges":{"votes":0,"viewingMemberVoted":false,"subscribed":false,"fogbugz":"","checkItems":0,"checkItemsChecked":0,"comments":0,"attachments":0,"description":false,"due":null},"checkItemStates":[],"closed":false,"dateLastActivity":"2015-04-15T18:08:56.731Z","desc":"","descData":null,"due":null,"email":null,"idBoard":"5510ea66af1945352b1c986c","idChecklists":[],"idList":"5510ea73de7581316ca2cad9","idMembers":[],"idMembersVoted":[],"idShort":20,"idAttachmentCover":null,"manualCoverAttachment":false,"labels":[],"idLabels":[],"name":"２〜３人のチーム向けマネジメントツール","pos":589823,"shortLink":"3yyFQL2t","shortUrl":"https://trello.com/c/3yyFQL2t","subscribed":null,"url":"https://trello.com/c/3yyFQL2t/20--","attachments":[]},{"id":"554afa850d84e49f5abedbdf","badges":{"votes":0,"viewingMemberVoted":false,"subscribed":false,"fogbugz":"","checkItems":0,"checkItemsChecked":0,"comments":0,"attachments":0,"description":false,"due":null},"checkItemStates":[],"closed":false,"dateLastActivity":"2015-05-07T05:39:17.518Z","desc":"","descData":null,"due":null,"email":null,"idBoard":"5510ea66af1945352b1c986c","idChecklists":[],"idList":"5510ea73de7581316ca2cad9","idMembers":[],"idMembersVoted":[],"idShort":23,"idAttachmentCover":null,"manualCoverAttachment":false,"labels":[],"idLabels":[],"name":"習慣付けを助けてくれるタスク管理ツール","pos":720895,"shortLink":"6k942jT8","shortUrl":"https://trello.com/c/6k942jT8","subscribed":null,"url":"https://trello.com/c/6k942jT8/23--","attachments":[]},{"id":"554afadc6593f3d895b90e9b","badges":{"votes":0,"viewingMemberVoted":false,"subscribed":false,"fogbugz":"","checkItems":0,"checkItemsChecked":0,"comments":0,"attachments":0,"description":false,"due":null},"checkItemStates":[],"closed":false,"dateLastActivity":"2015-05-07T05:40:44.112Z","desc":"","descData":null,"due":null,"email":null,"idBoard":"5510ea66af1945352b1c986c","idChecklists":[],"idList":"5510ea73de7581316ca2cad9","idMembers":[],"idMembersVoted":[],"idShort":24,"idAttachmentCover":null,"manualCoverAttachment":false,"labels":[],"idLabels":[],"name":"ボクセルからドット絵素材生成してくれるツール","pos":786431,"shortLink":"e2l22qt2","shortUrl":"https://trello.com/c/e2l22qt2","subscribed":null,"url":"https://trello.com/c/e2l22qt2/24--","attachments":[]},{"id":"554afb076529708b5ab7e53c","badges":{"votes":0,"viewingMemberVoted":false,"subscribed":false,"fogbugz":"","checkItems":0,"checkItemsChecked":0,"comments":0,"attachments":0,"description":false,"due":null},"checkItemStates":[],"closed":false,"dateLastActivity":"2015-05-07T05:41:27.332Z","desc":"","descData":null,"due":null,"email":null,"idBoard":"5510ea66af1945352b1c986c","idChecklists":[],"idList":"5510ea73de7581316ca2cad9","idMembers":[],"idMembersVoted":[],"idShort":25,"idAttachmentCover":null,"manualCoverAttachment":false,"labels":[],"idLabels":[],"name":"日課（毎日、毎週など）用のタスク管理ツール","pos":851967,"shortLink":"3UcolmO8","shortUrl":"https://trello.com/c/3UcolmO8","subscribed":null,"url":"https://trello.com/c/3UcolmO8/25--","attachments":[]},{"id":"554afb463f861743079ef715","badges":{"votes":0,"viewingMemberVoted":false,"subscribed":false,"fogbugz":"","checkItems":0,"checkItemsChecked":0,"comments":0,"attachments":0,"description":false,"due":null},"checkItemStates":[],"closed":false,"dateLastActivity":"2015-05-07T05:42:30.195Z","desc":"","descData":null,"due":null,"email":null,"idBoard":"5510ea66af1945352b1c986c","idChecklists":[],"idList":"5510ea73de7581316ca2cad9","idMembers":[],"idMembersVoted":[],"idShort":27,"idAttachmentCover":null,"manualCoverAttachment":false,"labels":[],"idLabels":[],"name":"Excel方眼紙の代わりになる作図ツール","pos":983039,"shortLink":"YswNi6bI","shortUrl":"https://trello.com/c/YswNi6bI","subscribed":null,"url":"https://trello.com/c/YswNi6bI/27-excel","attachments":[]},{"id":"554afbb497f17167dec9de66","badges":{"votes":0,"viewingMemberVoted":false,"subscribed":false,"fogbugz":"","checkItems":0,"checkItemsChecked":0,"comments":0,"attachments":0,"description":false,"due":null},"checkItemStates":[],"closed":false,"dateLastActivity":"2015-05-07T05:44:20.929Z","desc":"","descData":null,"due":null,"email":null,"idBoard":"5510ea66af1945352b1c986c","idChecklists":[],"idList":"5510ea73de7581316ca2cad9","idMembers":[],"idMembersVoted":[],"idShort":28,"idAttachmentCover":null,"manualCoverAttachment":false,"labels":[],"idLabels":[],"name":"「逆引きVue.js」解説サイト","pos":1048575,"shortLink":"yLyoZoyw","shortUrl":"https://trello.com/c/yLyoZoyw","subscribed":null,"url":"https://trello.com/c/yLyoZoyw/28-vue-js","attachments":[]},{"id":"554afbcef0ae5b3e9b128f9f","badges":{"votes":0,"viewingMemberVoted":false,"subscribed":false,"fogbugz":"","checkItems":0,"checkItemsChecked":0,"comments":0,"attachments":0,"description":false,"due":null},"checkItemStates":[],"closed":false,"dateLastActivity":"2015-05-07T05:44:46.043Z","desc":"","descData":null,"due":null,"email":null,"idBoard":"5510ea66af1945352b1c986c","idChecklists":[],"idList":"5510ea73de7581316ca2cad9","idMembers":[],"idMembersVoted":[],"idShort":30,"idAttachmentCover":null,"manualCoverAttachment":false,"labels":[],"idLabels":[],"name":"名刺、六角形ステッカー","pos":1179647,"shortLink":"DE8aOOiW","shortUrl":"https://trello.com/c/DE8aOOiW","subscribed":null,"url":"https://trello.com/c/DE8aOOiW/30--","attachments":[]},{"id":"554afbc08aaf6a110770da54","badges":{"votes":0,"viewingMemberVoted":false,"subscribed":false,"fogbugz":"","checkItems":0,"checkItemsChecked":0,"comments":0,"attachments":0,"description":false,"due":null},"checkItemStates":[],"closed":false,"dateLastActivity":"2015-05-07T05:45:48.559Z","desc":"","descData":null,"due":null,"email":null,"idBoard":"5510ea66af1945352b1c986c","idChecklists":[],"idList":"5510ea73de7581316ca2cad9","idMembers":[],"idMembersVoted":[],"idShort":29,"idAttachmentCover":null,"manualCoverAttachment":false,"labels":[],"idLabels":[],"name":"DevHubの宣伝サイト","pos":1245183,"shortLink":"WGCrJD08","shortUrl":"https://trello.com/c/WGCrJD08","subscribed":null,"url":"https://trello.com/c/WGCrJD08/29-devhub","attachments":[]},{"id":"554afc6daaaa1845deefb1fe","badges":{"votes":0,"viewingMemberVoted":false,"subscribed":false,"fogbugz":"","checkItems":0,"checkItemsChecked":0,"comments":0,"attachments":0,"description":false,"due":null},"checkItemStates":[],"closed":false,"dateLastActivity":"2015-05-07T05:47:25.849Z","desc":"","descData":null,"due":null,"email":null,"idBoard":"5510ea66af1945352b1c986c","idChecklists":[],"idList":"5510ea73de7581316ca2cad9","idMembers":[],"idMembersVoted":[],"idShort":31,"idAttachmentCover":null,"manualCoverAttachment":false,"labels":[],"idLabels":[],"name":"棒人間描くと、その場に人物描画してくれるツール","pos":1310719,"shortLink":"LwbD0na9","shortUrl":"https://trello.com/c/LwbD0na9","subscribed":null,"url":"https://trello.com/c/LwbD0na9/31--","attachments":[]},{"id":"554afd483bdd5ca2cf80be56","badges":{"votes":0,"viewingMemberVoted":false,"subscribed":false,"fogbugz":"","checkItems":0,"checkItemsChecked":0,"comments":2,"attachments":0,"description":false,"due":null},"checkItemStates":[],"closed":false,"dateLastActivity":"2015-05-07T06:09:05.973Z","desc":"","descData":null,"due":null,"email":null,"idBoard":"5510ea66af1945352b1c986c","idChecklists":[],"idList":"5510ea73de7581316ca2cad9","idMembers":[],"idMembersVoted":[],"idShort":32,"idAttachmentCover":null,"manualCoverAttachment":false,"labels":[],"idLabels":[],"name":"朝、出社時に簡単な計算問題を出して、その日の脳のパフォーマンスを記録・推測してくれるツール","pos":1376255,"shortLink":"27d9NPSd","shortUrl":"https://trello.com/c/27d9NPSd","subscribed":null,"url":"https://trello.com/c/27d9NPSd/32--","attachments":[]},{"id":"554afdd62db310dec61327c0","badges":{"votes":0,"viewingMemberVoted":false,"subscribed":false,"fogbugz":"","checkItems":0,"checkItemsChecked":0,"comments":0,"attachments":0,"description":false,"due":null},"checkItemStates":[],"closed":false,"dateLastActivity":"2015-05-07T05:53:26.097Z","desc":"","descData":null,"due":null,"email":null,"idBoard":"5510ea66af1945352b1c986c","idChecklists":[],"idList":"5510ea73de7581316ca2cad9","idMembers":[],"idMembersVoted":[],"idShort":33,"idAttachmentCover":null,"manualCoverAttachment":false,"labels":[],"idLabels":[],"name":"リアルタイム編集前提のWikiエンジン","pos":1441791,"shortLink":"RD9lrMEp","shortUrl":"https://trello.com/c/RD9lrMEp","subscribed":null,"url":"https://trello.com/c/RD9lrMEp/33-wiki","attachments":[]},{"id":"554afe1961aa4e13967275ff","badges":{"votes":0,"viewingMemberVoted":false,"subscribed":false,"fogbugz":"","checkItems":0,"checkItemsChecked":0,"comments":0,"attachments":0,"description":false,"due":null},"checkItemStates":[],"closed":false,"dateLastActivity":"2015-05-07T05:54:33.650Z","desc":"","descData":null,"due":null,"email":null,"idBoard":"5510ea66af1945352b1c986c","idChecklists":[],"idList":"5510ea73de7581316ca2cad9","idMembers":[],"idMembersVoted":[],"idShort":34,"idAttachmentCover":null,"manualCoverAttachment":false,"labels":[],"idLabels":[],"name":"Favしたツイートを一覧して、更にD&Dで分類保管できるツール","pos":1507327,"shortLink":"JbJevG19","shortUrl":"https://trello.com/c/JbJevG19","subscribed":null,"url":"https://trello.com/c/JbJevG19/34-fav-d-d","attachments":[]},{"id":"554afedb8232e1d583a08c7d","badges":{"votes":0,"viewingMemberVoted":false,"subscribed":false,"fogbugz":"","checkItems":0,"checkItemsChecked":0,"comments":0,"attachments":0,"description":false,"due":null},"checkItemStates":[],"closed":false,"dateLastActivity":"2015-05-07T05:57:47.735Z","desc":"","descData":null,"due":null,"email":null,"idBoard":"5510ea66af1945352b1c986c","idChecklists":[],"idList":"5510ea73de7581316ca2cad9","idMembers":[],"idMembersVoted":[],"idShort":35,"idAttachmentCover":null,"manualCoverAttachment":false,"labels":[],"idLabels":[],"name":"不思議な写真作成ツール。二枚写真を撮って、箇所ごとにどちらの写真を使うか指定できる。重ねあわせは自動。","pos":1572863,"shortLink":"SYxwq6b0","shortUrl":"https://trello.com/c/SYxwq6b0","subscribed":null,"url":"https://trello.com/c/SYxwq6b0/35--","attachments":[]},{"id":"554aff0f1fa8b0b166e6cd79","badges":{"votes":0,"viewingMemberVoted":false,"subscribed":false,"fogbugz":"","checkItems":0,"checkItemsChecked":0,"comments":0,"attachments":0,"description":false,"due":null},"checkItemStates":[],"closed":false,"dateLastActivity":"2015-05-07T05:58:48.657Z","desc":"","descData":null,"due":null,"email":null,"idBoard":"5510ea66af1945352b1c986c","idChecklists":[],"idList":"5510ea73de7581316ca2cad9","idMembers":[],"idMembersVoted":[],"idShort":36,"idAttachmentCover":null,"manualCoverAttachment":false,"labels":[],"idLabels":[],"name":"横視点の簡易Civ","pos":1638399,"shortLink":"wOLwHgPp","shortUrl":"https://trello.com/c/wOLwHgPp","subscribed":null,"url":"https://trello.com/c/wOLwHgPp/36-civ","attachments":[]},{"id":"557344c1b0ce37273869099f","badges":{"votes":0,"viewingMemberVoted":false,"subscribed":false,"fogbugz":"","checkItems":0,"checkItemsChecked":0,"comments":0,"attachments":0,"description":false,"due":null},"checkItemStates":[],"closed":false,"dateLastActivity":"2015-06-06T19:06:41.697Z","desc":"","descData":null,"due":null,"email":null,"idBoard":"5510ea66af1945352b1c986c","idChecklists":[],"idList":"5510ea73de7581316ca2cad9","idMembers":[],"idMembersVoted":[],"idShort":39,"idAttachmentCover":null,"manualCoverAttachment":false,"labels":[],"idLabels":[],"name":"アイコンその場編集用の超ミニSVGエディタ","pos":1703935,"shortLink":"oOSZXbMs","shortUrl":"https://trello.com/c/oOSZXbMs","subscribed":null,"url":"https://trello.com/c/oOSZXbMs/39-svg","attachments":[]},{"id":"5510ec6e77cfd09044149945","badges":{"votes":0,"viewingMemberVoted":false,"subscribed":false,"fogbugz":"","checkItems":0,"checkItemsChecked":0,"comments":0,"attachments":0,"description":false,"due":null},"checkItemStates":[],"closed":false,"dateLastActivity":"2015-03-24T04:47:42.545Z","desc":"","descData":null,"due":null,"email":null,"idBoard":"5510ea66af1945352b1c986c","idChecklists":[],"idList":"5510ec6028268c45e167bde6","idMembers":[],"idMembersVoted":[],"idShort":4,"idAttachmentCover":null,"manualCoverAttachment":false,"labels":[],"idLabels":[],"name":"もっとワークフローをゲーミフィケーション化したい","pos":65535,"shortLink":"Rg5HciTA","shortUrl":"https://trello.com/c/Rg5HciTA","subscribed":null,"url":"https://trello.com/c/Rg5HciTA/4--","attachments":[]},{"id":"5510ec77869b8210d9a855b9","badges":{"votes":0,"viewingMemberVoted":false,"subscribed":false,"fogbugz":"","checkItems":0,"checkItemsChecked":0,"comments":0,"attachments":0,"description":false,"due":null},"checkItemStates":[],"closed":false,"dateLastActivity":"2015-03-24T04:47:51.481Z","desc":"","descData":null,"due":null,"email":null,"idBoard":"5510ea66af1945352b1c986c","idChecklists":[],"idList":"5510ec6028268c45e167bde6","idMembers":[],"idMembersVoted":[],"idShort":5,"idAttachmentCover":null,"manualCoverAttachment":false,"labels":[],"idLabels":[],"name":"ドキュメント作成を楽にしたい","pos":131071,"shortLink":"X1G89hMF","shortUrl":"https://trello.com/c/X1G89hMF","subscribed":null,"url":"https://trello.com/c/X1G89hMF/5--","attachments":[]},{"id":"5510ec8a8fa9d9e07126b6d2","badges":{"votes":0,"viewingMemberVoted":false,"subscribed":false,"fogbugz":"","checkItems":0,"checkItemsChecked":0,"comments":0,"attachments":0,"description":false,"due":null},"checkItemStates":[],"closed":false,"dateLastActivity":"2015-03-24T04:48:10.831Z","desc":"","descData":null,"due":null,"email":null,"idBoard":"5510ea66af1945352b1c986c","idChecklists":[],"idList":"5510ec6028268c45e167bde6","idMembers":[],"idMembersVoted":[],"idShort":6,"idAttachmentCover":null,"manualCoverAttachment":false,"labels":[],"idLabels":[],"name":"既存のツールをモードレスに作り替えたい","pos":196607,"shortLink":"6gPk0mdY","shortUrl":"https://trello.com/c/6gPk0mdY","subscribed":null,"url":"https://trello.com/c/6gPk0mdY/6--","attachments":[]},{"id":"5510ecc65db284e4fbc21a5e","badges":{"votes":0,"viewingMemberVoted":false,"subscribed":false,"fogbugz":"","checkItems":0,"checkItemsChecked":0,"comments":0,"attachments":0,"description":false,"due":null},"checkItemStates":[],"closed":false,"dateLastActivity":"2015-03-24T04:49:10.876Z","desc":"","descData":null,"due":null,"email":null,"idBoard":"5510ea66af1945352b1c986c","idChecklists":[],"idList":"5510ec6028268c45e167bde6","idMembers":[],"idMembersVoted":[],"idShort":7,"idAttachmentCover":null,"manualCoverAttachment":false,"labels":[],"idLabels":[],"name":"ツールの「かわいさ（モードレス、ミニマル、直接編集）」を大事にしたい","pos":262143,"shortLink":"cJxA50lS","shortUrl":"https://trello.com/c/cJxA50lS","subscribed":null,"url":"https://trello.com/c/cJxA50lS/7--","attachments":[]},{"id":"5510ecf2bdca3d9e9e3806a3","badges":{"votes":0,"viewingMemberVoted":false,"subscribed":false,"fogbugz":"","checkItems":0,"checkItemsChecked":0,"comments":0,"attachments":0,"description":false,"due":null},"checkItemStates":[],"closed":false,"dateLastActivity":"2015-03-24T04:49:54.680Z","desc":"","descData":null,"due":null,"email":null,"idBoard":"5510ea66af1945352b1c986c","idChecklists":[],"idList":"5510ec6028268c45e167bde6","idMembers":[],"idMembersVoted":[],"idShort":8,"idAttachmentCover":null,"manualCoverAttachment":false,"labels":[],"idLabels":[],"name":"脳の模倣","pos":327679,"shortLink":"dQu6HGm9","shortUrl":"https://trello.com/c/dQu6HGm9","subscribed":null,"url":"https://trello.com/c/dQu6HGm9/8--","attachments":[]},{"id":"5510ecfecea97e4f44eccbb4","badges":{"votes":0,"viewingMemberVoted":false,"subscribed":false,"fogbugz":"","checkItems":0,"checkItemsChecked":0,"comments":0,"attachments":0,"description":false,"due":null},"checkItemStates":[],"closed":false,"dateLastActivity":"2015-03-24T04:50:06.884Z","desc":"","descData":null,"due":null,"email":null,"idBoard":"5510ea66af1945352b1c986c","idChecklists":[],"idList":"5510ec6028268c45e167bde6","idMembers":[],"idMembersVoted":[],"idShort":9,"idAttachmentCover":null,"manualCoverAttachment":false,"labels":[],"idLabels":[],"name":"紙ベースワークフローの簡易な代替","pos":393215,"shortLink":"nQaDEBJ9","shortUrl":"https://trello.com/c/nQaDEBJ9","subscribed":null,"url":"https://trello.com/c/nQaDEBJ9/9--","attachments":[]},{"id":"5510f31f71a2d428d9dfa6dd","badges":{"votes":0,"viewingMemberVoted":false,"subscribed":false,"fogbugz":"","checkItems":0,"checkItemsChecked":0,"comments":0,"attachments":0,"description":false,"due":null},"checkItemStates":[],"closed":false,"dateLastActivity":"2015-03-24T05:16:15.812Z","desc":"","descData":null,"due":null,"email":null,"idBoard":"5510ea66af1945352b1c986c","idChecklists":[],"idList":"5510ec6028268c45e167bde6","idMembers":[],"idMembersVoted":[],"idShort":17,"idAttachmentCover":null,"manualCoverAttachment":false,"labels":[],"idLabels":[],"name":"Vue.jsのプロジェクトテンプレート吐くツール","pos":458751,"shortLink":"tRYkXdNs","shortUrl":"https://trello.com/c/tRYkXdNs","subscribed":null,"url":"https://trello.com/c/tRYkXdNs/17-vue-js","attachments":[]},{"id":"554affe76f75be9bb7f1fa7f","badges":{"votes":0,"viewingMemberVoted":false,"subscribed":false,"fogbugz":"","checkItems":0,"checkItemsChecked":0,"comments":0,"attachments":0,"description":false,"due":null},"checkItemStates":[],"closed":false,"dateLastActivity":"2015-05-07T06:02:15.879Z","desc":"","descData":null,"due":null,"email":null,"idBoard":"5510ea66af1945352b1c986c","idChecklists":[],"idList":"5510ec6028268c45e167bde6","idMembers":[],"idMembersVoted":[],"idShort":37,"idAttachmentCover":null,"manualCoverAttachment":false,"labels":[],"idLabels":[],"name":"自分に出来る事を公開して、ちょっとしたことをお手伝いできる「肩たたき券」みたいなのを発行したい。","pos":524287,"shortLink":"BYEuw7WA","shortUrl":"https://trello.com/c/BYEuw7WA","subscribed":null,"url":"https://trello.com/c/BYEuw7WA/37--","attachments":[]},{"id":"554b005facc874b056aa0a03","badges":{"votes":0,"viewingMemberVoted":false,"subscribed":false,"fogbugz":"","checkItems":0,"checkItemsChecked":0,"comments":0,"attachments":0,"description":false,"due":null},"checkItemStates":[],"closed":false,"dateLastActivity":"2015-05-07T06:04:15.284Z","desc":"","descData":null,"due":null,"email":null,"idBoard":"5510ea66af1945352b1c986c","idChecklists":[],"idList":"5510ec6028268c45e167bde6","idMembers":[],"idMembersVoted":[],"idShort":38,"idAttachmentCover":null,"manualCoverAttachment":false,"labels":[],"idLabels":[],"name":"勉強会で、みんな同じサイトにアクセスして、興味分野をマッピングなどで示して、懇親会のマッチングができるサイト","pos":589823,"shortLink":"KHIyczsf","shortUrl":"https://trello.com/c/KHIyczsf","subscribed":null,"url":"https://trello.com/c/KHIyczsf/38--","attachments":[]},{"id":"5510f19583a4b64c44e66e80","badges":{"votes":0,"viewingMemberVoted":false,"subscribed":false,"fogbugz":"","checkItems":0,"checkItemsChecked":0,"comments":0,"attachments":0,"description":false,"due":null},"checkItemStates":[],"closed":false,"dateLastActivity":"2015-04-15T18:09:22.580Z","desc":"","descData":null,"due":null,"email":null,"idBoard":"5510ea66af1945352b1c986c","idChecklists":[],"idList":"552c7192acf369a608112162","idMembers":[],"idMembersVoted":[],"idShort":16,"idAttachmentCover":null,"manualCoverAttachment":false,"labels":[],"idLabels":[],"name":"Trello API渡すと、JSONで吐いてくれるツール","pos":32767.5,"shortLink":"ayx8v1po","shortUrl":"https://trello.com/c/ayx8v1po","subscribed":null,"url":"https://trello.com/c/ayx8v1po/16-trello-api-json","attachments":[]},{"id":"5510eb6f83a4b64c44e66a64","badges":{"votes":0,"viewingMemberVoted":false,"subscribed":false,"fogbugz":"","checkItems":0,"checkItemsChecked":0,"comments":1,"attachments":0,"description":false,"due":null},"checkItemStates":[],"closed":false,"dateLastActivity":"2015-04-14T01:47:26.159Z","desc":"","descData":null,"due":null,"email":null,"idBoard":"5510ea66af1945352b1c986c","idChecklists":[],"idList":"552c7192acf369a608112162","idMembers":[],"idMembersVoted":[],"idShort":2,"idAttachmentCover":null,"manualCoverAttachment":false,"labels":[],"idLabels":[],"name":"Trelloからきれいなランディングページ生成ツール","pos":65535,"shortLink":"XYfGATes","shortUrl":"https://trello.com/c/XYfGATes","subscribed":null,"url":"https://trello.com/c/XYfGATes/2-trello","attachments":[]},{"id":"5510f16cad10f449d94a44e9","badges":{"votes":0,"viewingMemberVoted":false,"subscribed":false,"fogbugz":"","checkItems":0,"checkItemsChecked":0,"comments":0,"attachments":0,"description":false,"due":null},"checkItemStates":[],"closed":false,"dateLastActivity":"2015-04-15T18:09:35.739Z","desc":"","descData":null,"due":null,"email":null,"idBoard":"5510ea66af1945352b1c986c","idChecklists":[],"idList":"552c7192acf369a608112162","idMembers":[],"idMembersVoted":[],"idShort":15,"idAttachmentCover":null,"manualCoverAttachment":false,"labels":[],"idLabels":[],"name":"JSONのURLを指定すると、いい感じに整形してくれるサイト","pos":393215,"shortLink":"tlMcjcld","shortUrl":"https://trello.com/c/tlMcjcld","subscribed":null,"url":"https://trello.com/c/tlMcjcld/15-json-url","attachments":[]}],"actions":[{"id":"557344fad919dcc0f0d0de85","idMemberCreator":"53c797959cd0710742a14dce","data":{"listAfter":{"name":"作ってる","id":"5510ea77b882b3677c740157"},"listBefore":{"name":"作りたい","id":"5510ea73de7581316ca2cad9"},"board":{"shortLink":"VusqcRPc","name":"Product","id":"5510ea66af1945352b1c986c"},"card":{"shortLink":"Jhr5wRzh","idShort":21,"name":"ビルドごとに、撮影したgifをアップロードする場所","id":"5548c8772f9163a228decda4","idList":"5510ea77b882b3677c740157"},"old":{"idList":"5510ea73de7581316ca2cad9"}},"type":"updateCard","date":"2015-06-06T19:07:38.554Z","memberCreator":{"id":"53c797959cd0710742a14dce","avatarHash":null,"fullName":"hash rock","initials":"HR","username":"hashrock"}},{"id":"557344c1b0ce3727386909a0","idMemberCreator":"53c797959cd0710742a14dce","data":{"board":{"shortLink":"VusqcRPc","name":"Product","id":"5510ea66af1945352b1c986c"},"list":{"name":"作りたい","id":"5510ea73de7581316ca2cad9"},"card":{"shortLink":"oOSZXbMs","idShort":39,"name":"アイコンその場編集用の超ミニSVGエディタ","id":"557344c1b0ce37273869099f"}},"type":"createCard","date":"2015-06-06T19:06:41.712Z","memberCreator":{"id":"53c797959cd0710742a14dce","avatarHash":null,"fullName":"hash rock","initials":"HR","username":"hashrock"}},{"id":"55734458b0ce372738690977","idMemberCreator":"53c797959cd0710742a14dce","data":{"list":{"name":"作ってる","id":"5510ea77b882b3677c740157"},"board":{"shortLink":"VusqcRPc","name":"Product","id":"5510ea66af1945352b1c986c"},"card":{"shortLink":"ulWZm2CN","idShort":26,"name":"テスト項目書をExcelで書かなくて済むツール","id":"554afb35fe40cfba66515192","pos":557055},"old":{"pos":917503}},"type":"updateCard","date":"2015-06-06T19:04:56.631Z","memberCreator":{"id":"53c797959cd0710742a14dce","avatarHash":null,"fullName":"hash rock","initials":"HR","username":"hashrock"}},{"id":"55734458b0ce372738690976","idMemberCreator":"53c797959cd0710742a14dce","data":{"listAfter":{"name":"作ってる","id":"5510ea77b882b3677c740157"},"listBefore":{"name":"作りたい","id":"5510ea73de7581316ca2cad9"},"board":{"shortLink":"VusqcRPc","name":"Product","id":"5510ea66af1945352b1c986c"},"card":{"shortLink":"ulWZm2CN","idShort":26,"name":"テスト項目書をExcelで書かなくて済むツール","id":"554afb35fe40cfba66515192","idList":"5510ea77b882b3677c740157"},"old":{"idList":"5510ea73de7581316ca2cad9"}},"type":"updateCard","date":"2015-06-06T19:04:56.598Z","memberCreator":{"id":"53c797959cd0710742a14dce","avatarHash":null,"fullName":"hash rock","initials":"HR","username":"hashrock"}},{"id":"55734291679c3cfd2c6bec7f","idMemberCreator":"53c797959cd0710742a14dce","data":{"list":{"name":"作ってる","id":"5510ea77b882b3677c740157"},"board":{"shortLink":"VusqcRPc","name":"Product","id":"5510ea66af1945352b1c986c"},"card":{"shortLink":"3a5beVlC","idShort":11,"name":"かんたんGIFエディタ","id":"5510eea03d17d51bff96327c","pos":589823},"old":{"pos":196607}},"type":"updateCard","date":"2015-06-06T18:57:21.926Z","memberCreator":{"id":"53c797959cd0710742a14dce","avatarHash":null,"fullName":"hash rock","initials":"HR","username":"hashrock"}},{"id":"55734291679c3cfd2c6bec7e","idMemberCreator":"53c797959cd0710742a14dce","data":{"listAfter":{"name":"作ってる","id":"5510ea77b882b3677c740157"},"listBefore":{"name":"作りたい","id":"5510ea73de7581316ca2cad9"},"board":{"shortLink":"VusqcRPc","name":"Product","id":"5510ea66af1945352b1c986c"},"card":{"shortLink":"3a5beVlC","idShort":11,"name":"かんたんGIFエディタ","id":"5510eea03d17d51bff96327c","idList":"5510ea77b882b3677c740157"},"old":{"idList":"5510ea73de7581316ca2cad9"}},"type":"updateCard","date":"2015-06-06T18:57:21.878Z","memberCreator":{"id":"53c797959cd0710742a14dce","avatarHash":null,"fullName":"hash rock","initials":"HR","username":"hashrock"}},{"id":"554b269cc89aae5f8fc326b7","idMemberCreator":"53c797959cd0710742a14dce","data":{"listAfter":{"name":"作ってる","id":"5510ea77b882b3677c740157"},"listBefore":{"name":"作りたい","id":"5510ea73de7581316ca2cad9"},"board":{"shortLink":"VusqcRPc","name":"Product","id":"5510ea66af1945352b1c986c"},"card":{"shortLink":"ZhPysPZq","idShort":18,"name":"ライトウェイトなカンバンツール","id":"55123b647ed28b7bccbba95e","idList":"5510ea77b882b3677c740157"},"old":{"idList":"5510ea73de7581316ca2cad9"}},"type":"updateCard","date":"2015-05-07T08:47:24.258Z","memberCreator":{"id":"53c797959cd0710742a14dce","avatarHash":null,"fullName":"hash rock","initials":"HR","username":"hashrock"}},{"id":"554b268a2d7fb6d6954651fc","idMemberCreator":"53c797959cd0710742a14dce","data":{"list":{"name":"作りたい","id":"5510ea73de7581316ca2cad9"},"board":{"shortLink":"VusqcRPc","name":"Product","id":"5510ea66af1945352b1c986c"},"card":{"shortLink":"ZhPysPZq","idShort":18,"name":"ライトウェイトなカンバンツール","id":"55123b647ed28b7bccbba95e"},"text":"「One sushi tray team（２〜４人）」向けタスク管理、というキャッチコピーを考えた。"},"type":"commentCard","date":"2015-05-07T08:47:06.581Z","memberCreator":{"id":"53c797959cd0710742a14dce","avatarHash":null,"fullName":"hash rock","initials":"HR","username":"hashrock"}},{"id":"554b0181d76dea7ffba0ee7e","idMemberCreator":"53c797959cd0710742a14dce","data":{"list":{"name":"作りたい","id":"5510ea73de7581316ca2cad9"},"board":{"shortLink":"VusqcRPc","name":"Product","id":"5510ea66af1945352b1c986c"},"card":{"shortLink":"27d9NPSd","idShort":32,"name":"朝、出社時に簡単な計算問題を出して、その日の脳のパフォーマンスを記録・推測してくれるツール","id":"554afd483bdd5ca2cf80be56"},"text":"課題はN-backがいいと思う（訓練効果も期待できる）"},"type":"commentCard","date":"2015-05-07T06:09:05.974Z","memberCreator":{"id":"53c797959cd0710742a14dce","avatarHash":null,"fullName":"hash rock","initials":"HR","username":"hashrock"}},{"id":"554b00c3dd8ffc9853ac1c90","idMemberCreator":"53c797959cd0710742a14dce","data":{"list":{"name":"作りたい","id":"5510ea73de7581316ca2cad9"},"board":{"shortLink":"VusqcRPc","name":"Product","id":"5510ea66af1945352b1c986c"},"card":{"shortLink":"ZhPysPZq","idShort":18,"name":"ライトウェイトなカンバンツール","id":"55123b647ed28b7bccbba95e"},"text":"Excelシート並に、その場で作って捨てられるものがいい。Windows上でサーバが建てられるといいかも？"},"type":"commentCard","date":"2015-05-07T06:05:55.274Z","memberCreator":{"id":"53c797959cd0710742a14dce","avatarHash":null,"fullName":"hash rock","initials":"HR","username":"hashrock"}},{"id":"554b005facc874b056aa0a04","idMemberCreator":"53c797959cd0710742a14dce","data":{"board":{"shortLink":"VusqcRPc","name":"Product","id":"5510ea66af1945352b1c986c"},"list":{"name":"ネタ","id":"5510ec6028268c45e167bde6"},"card":{"shortLink":"KHIyczsf","idShort":38,"name":"勉強会で、みんな同じサイトにアクセスして、興味分野をマッピングなどで示して、懇親会のマッチングができるサイト","id":"554b005facc874b056aa0a03"}},"type":"createCard","date":"2015-05-07T06:04:15.296Z","memberCreator":{"id":"53c797959cd0710742a14dce","avatarHash":null,"fullName":"hash rock","initials":"HR","username":"hashrock"}},{"id":"554affe76f75be9bb7f1fa80","idMemberCreator":"53c797959cd0710742a14dce","data":{"board":{"shortLink":"VusqcRPc","name":"Product","id":"5510ea66af1945352b1c986c"},"list":{"name":"ネタ","id":"5510ec6028268c45e167bde6"},"card":{"shortLink":"BYEuw7WA","idShort":37,"name":"自分に出来る事を公開して、ちょっとしたことをお手伝いできる「肩たたき券」みたいなのを発行したい。","id":"554affe76f75be9bb7f1fa7f"}},"type":"createCard","date":"2015-05-07T06:02:15.934Z","memberCreator":{"id":"53c797959cd0710742a14dce","avatarHash":null,"fullName":"hash rock","initials":"HR","username":"hashrock"}},{"id":"554aff1897a1f9af56b189be","idMemberCreator":"53c797959cd0710742a14dce","data":{"list":{"name":"作りたい","id":"5510ea73de7581316ca2cad9"},"board":{"shortLink":"VusqcRPc","name":"Product","id":"5510ea66af1945352b1c986c"},"card":{"shortLink":"wOLwHgPp","idShort":36,"id":"554aff0f1fa8b0b166e6cd79","name":"横視点の簡易Civ"},"old":{"name":"横視点のCiv"}},"type":"updateCard","date":"2015-05-07T05:58:48.666Z","memberCreator":{"id":"53c797959cd0710742a14dce","avatarHash":null,"fullName":"hash rock","initials":"HR","username":"hashrock"}},{"id":"554aff0f1fa8b0b166e6cd7a","idMemberCreator":"53c797959cd0710742a14dce","data":{"board":{"shortLink":"VusqcRPc","name":"Product","id":"5510ea66af1945352b1c986c"},"list":{"name":"作りたい","id":"5510ea73de7581316ca2cad9"},"card":{"shortLink":"wOLwHgPp","idShort":36,"name":"横視点のCiv","id":"554aff0f1fa8b0b166e6cd79"}},"type":"createCard","date":"2015-05-07T05:58:39.542Z","memberCreator":{"id":"53c797959cd0710742a14dce","avatarHash":null,"fullName":"hash rock","initials":"HR","username":"hashrock"}},{"id":"554afedb8232e1d583a08c7e","idMemberCreator":"53c797959cd0710742a14dce","data":{"board":{"shortLink":"VusqcRPc","name":"Product","id":"5510ea66af1945352b1c986c"},"list":{"name":"作りたい","id":"5510ea73de7581316ca2cad9"},"card":{"shortLink":"SYxwq6b0","idShort":35,"name":"不思議な写真作成ツール。二枚写真を撮って、箇所ごとにどちらの写真を使うか指定できる。重ねあわせは自動。","id":"554afedb8232e1d583a08c7d"}},"type":"createCard","date":"2015-05-07T05:57:47.747Z","memberCreator":{"id":"53c797959cd0710742a14dce","avatarHash":null,"fullName":"hash rock","initials":"HR","username":"hashrock"}},{"id":"554afe1961aa4e1396727600","idMemberCreator":"53c797959cd0710742a14dce","data":{"board":{"shortLink":"VusqcRPc","name":"Product","id":"5510ea66af1945352b1c986c"},"list":{"name":"作りたい","id":"5510ea73de7581316ca2cad9"},"card":{"shortLink":"JbJevG19","idShort":34,"name":"Favしたツイートを一覧して、更にD&Dで分類保管できるツール","id":"554afe1961aa4e13967275ff"}},"type":"createCard","date":"2015-05-07T05:54:33.661Z","memberCreator":{"id":"53c797959cd0710742a14dce","avatarHash":null,"fullName":"hash rock","initials":"HR","username":"hashrock"}},{"id":"554afdd62db310dec61327c1","idMemberCreator":"53c797959cd0710742a14dce","data":{"board":{"shortLink":"VusqcRPc","name":"Product","id":"5510ea66af1945352b1c986c"},"list":{"name":"作りたい","id":"5510ea73de7581316ca2cad9"},"card":{"shortLink":"RD9lrMEp","idShort":33,"name":"リアルタイム編集前提のWikiエンジン","id":"554afdd62db310dec61327c0"}},"type":"createCard","date":"2015-05-07T05:53:26.107Z","memberCreator":{"id":"53c797959cd0710742a14dce","avatarHash":null,"fullName":"hash rock","initials":"HR","username":"hashrock"}},{"id":"554afd85f45b117483d27059","idMemberCreator":"53c797959cd0710742a14dce","data":{"list":{"name":"作りたい","id":"5510ea73de7581316ca2cad9"},"board":{"shortLink":"VusqcRPc","name":"Product","id":"5510ea66af1945352b1c986c"},"card":{"shortLink":"27d9NPSd","idShort":32,"name":"朝、出社時に簡単な計算問題を出して、その日の脳のパフォーマンスを記録・推測してくれるツール","id":"554afd483bdd5ca2cf80be56"},"text":"同時に前日何時に寝たかを記録しておくことで、ベストな睡眠時間を把握することができる（かも）"},"type":"commentCard","date":"2015-05-07T05:52:05.310Z","memberCreator":{"id":"53c797959cd0710742a14dce","avatarHash":null,"fullName":"hash rock","initials":"HR","username":"hashrock"}},{"id":"554afd483bdd5ca2cf80be57","idMemberCreator":"53c797959cd0710742a14dce","data":{"board":{"shortLink":"VusqcRPc","name":"Product","id":"5510ea66af1945352b1c986c"},"list":{"name":"作りたい","id":"5510ea73de7581316ca2cad9"},"card":{"shortLink":"27d9NPSd","idShort":32,"name":"朝、出社時に簡単な計算問題を出して、その日の脳のパフォーマンスを記録・推測してくれるツール","id":"554afd483bdd5ca2cf80be56"}},"type":"createCard","date":"2015-05-07T05:51:04.530Z","memberCreator":{"id":"53c797959cd0710742a14dce","avatarHash":null,"fullName":"hash rock","initials":"HR","username":"hashrock"}},{"id":"554afc6daaaa1845deefb1ff","idMemberCreator":"53c797959cd0710742a14dce","data":{"board":{"shortLink":"VusqcRPc","name":"Product","id":"5510ea66af1945352b1c986c"},"list":{"name":"作りたい","id":"5510ea73de7581316ca2cad9"},"card":{"shortLink":"LwbD0na9","idShort":31,"name":"棒人間描くと、その場に人物描画してくれるツール","id":"554afc6daaaa1845deefb1fe"}},"type":"createCard","date":"2015-05-07T05:47:25.860Z","memberCreator":{"id":"53c797959cd0710742a14dce","avatarHash":null,"fullName":"hash rock","initials":"HR","username":"hashrock"}},{"id":"554afc0ce6a9222696f3f9fd","idMemberCreator":"53c797959cd0710742a14dce","data":{"list":{"name":"作りたい","id":"5510ea73de7581316ca2cad9"},"board":{"shortLink":"VusqcRPc","name":"Product","id":"5510ea66af1945352b1c986c"},"card":{"shortLink":"WGCrJD08","idShort":29,"name":"DevHubの宣伝サイト","id":"554afbc08aaf6a110770da54","pos":1245183},"old":{"pos":1114111}},"type":"updateCard","date":"2015-05-07T05:45:48.564Z","memberCreator":{"id":"53c797959cd0710742a14dce","avatarHash":null,"fullName":"hash rock","initials":"HR","username":"hashrock"}},{"id":"554afbcef0ae5b3e9b128fa0","idMemberCreator":"53c797959cd0710742a14dce","data":{"board":{"shortLink":"VusqcRPc","name":"Product","id":"5510ea66af1945352b1c986c"},"list":{"name":"作りたい","id":"5510ea73de7581316ca2cad9"},"card":{"shortLink":"DE8aOOiW","idShort":30,"name":"名刺、六角形ステッカー","id":"554afbcef0ae5b3e9b128f9f"}},"type":"createCard","date":"2015-05-07T05:44:46.053Z","memberCreator":{"id":"53c797959cd0710742a14dce","avatarHash":null,"fullName":"hash rock","initials":"HR","username":"hashrock"}},{"id":"554afbc08aaf6a110770da55","idMemberCreator":"53c797959cd0710742a14dce","data":{"board":{"shortLink":"VusqcRPc","name":"Product","id":"5510ea66af1945352b1c986c"},"list":{"name":"作りたい","id":"5510ea73de7581316ca2cad9"},"card":{"shortLink":"WGCrJD08","idShort":29,"name":"DevHubの宣伝サイト","id":"554afbc08aaf6a110770da54"}},"type":"createCard","date":"2015-05-07T05:44:32.522Z","memberCreator":{"id":"53c797959cd0710742a14dce","avatarHash":null,"fullName":"hash rock","initials":"HR","username":"hashrock"}},{"id":"554afbb497f17167dec9de67","idMemberCreator":"53c797959cd0710742a14dce","data":{"board":{"shortLink":"VusqcRPc","name":"Product","id":"5510ea66af1945352b1c986c"},"list":{"name":"作りたい","id":"5510ea73de7581316ca2cad9"},"card":{"shortLink":"yLyoZoyw","idShort":28,"name":"「逆引きVue.js」解説サイト","id":"554afbb497f17167dec9de66"}},"type":"createCard","date":"2015-05-07T05:44:20.939Z","memberCreator":{"id":"53c797959cd0710742a14dce","avatarHash":null,"fullName":"hash rock","initials":"HR","username":"hashrock"}},{"id":"554afb463f861743079ef716","idMemberCreator":"53c797959cd0710742a14dce","data":{"board":{"shortLink":"VusqcRPc","name":"Product","id":"5510ea66af1945352b1c986c"},"list":{"name":"作りたい","id":"5510ea73de7581316ca2cad9"},"card":{"shortLink":"YswNi6bI","idShort":27,"name":"Excel方眼紙の代わりになる作図ツール","id":"554afb463f861743079ef715"}},"type":"createCard","date":"2015-05-07T05:42:30.207Z","memberCreator":{"id":"53c797959cd0710742a14dce","avatarHash":null,"fullName":"hash rock","initials":"HR","username":"hashrock"}},{"id":"554afb36fe40cfba66515193","idMemberCreator":"53c797959cd0710742a14dce","data":{"board":{"shortLink":"VusqcRPc","name":"Product","id":"5510ea66af1945352b1c986c"},"list":{"name":"作りたい","id":"5510ea73de7581316ca2cad9"},"card":{"shortLink":"ulWZm2CN","idShort":26,"name":"テスト項目書をExcelで書かなくて済むツール","id":"554afb35fe40cfba66515192"}},"type":"createCard","date":"2015-05-07T05:42:14.016Z","memberCreator":{"id":"53c797959cd0710742a14dce","avatarHash":null,"fullName":"hash rock","initials":"HR","username":"hashrock"}},{"id":"554afb076529708b5ab7e53d","idMemberCreator":"53c797959cd0710742a14dce","data":{"board":{"shortLink":"VusqcRPc","name":"Product","id":"5510ea66af1945352b1c986c"},"list":{"name":"作りたい","id":"5510ea73de7581316ca2cad9"},"card":{"shortLink":"3UcolmO8","idShort":25,"name":"日課（毎日、毎週など）用のタスク管理ツール","id":"554afb076529708b5ab7e53c"}},"type":"createCard","date":"2015-05-07T05:41:27.343Z","memberCreator":{"id":"53c797959cd0710742a14dce","avatarHash":null,"fullName":"hash rock","initials":"HR","username":"hashrock"}},{"id":"554afadc6593f3d895b90e9c","idMemberCreator":"53c797959cd0710742a14dce","data":{"board":{"shortLink":"VusqcRPc","name":"Product","id":"5510ea66af1945352b1c986c"},"list":{"name":"作りたい","id":"5510ea73de7581316ca2cad9"},"card":{"shortLink":"e2l22qt2","idShort":24,"name":"ボクセルからドット絵素材生成してくれるツール","id":"554afadc6593f3d895b90e9b"}},"type":"createCard","date":"2015-05-07T05:40:44.127Z","memberCreator":{"id":"53c797959cd0710742a14dce","avatarHash":null,"fullName":"hash rock","initials":"HR","username":"hashrock"}},{"id":"554afab9507ce48c664b8a77","idMemberCreator":"53c797959cd0710742a14dce","data":{"list":{"name":"作った","id":"5510ea7a72e8aec6ec62bdac"},"board":{"shortLink":"VusqcRPc","name":"Product","id":"5510ea66af1945352b1c986c"},"card":{"shortLink":"gxIwLfgw","idShort":22,"name":"kanbandown","id":"554af9f2c279fd9fc6f2340e","pos":32767.5},"old":{"pos":98303}},"type":"updateCard","date":"2015-05-07T05:40:09.645Z","memberCreator":{"id":"53c797959cd0710742a14dce","avatarHash":null,"fullName":"hash rock","initials":"HR","username":"hashrock"}},{"id":"554afab7217f648ede1f57eb","idMemberCreator":"53c797959cd0710742a14dce","data":{"list":{"name":"作った","id":"5510ea7a72e8aec6ec62bdac"},"board":{"shortLink":"VusqcRPc","name":"Product","id":"5510ea66af1945352b1c986c"},"card":{"shortLink":"gxIwLfgw","idShort":22,"name":"kanbandown","id":"554af9f2c279fd9fc6f2340e","pos":98303},"old":{"pos":262143}},"type":"updateCard","date":"2015-05-07T05:40:07.291Z","memberCreator":{"id":"53c797959cd0710742a14dce","avatarHash":null,"fullName":"hash rock","initials":"HR","username":"hashrock"}},{"id":"554afa850d84e49f5abedbe0","idMemberCreator":"53c797959cd0710742a14dce","data":{"board":{"shortLink":"VusqcRPc","name":"Product","id":"5510ea66af1945352b1c986c"},"list":{"name":"作りたい","id":"5510ea73de7581316ca2cad9"},"card":{"shortLink":"6k942jT8","idShort":23,"name":"習慣付けを助けてくれるタスク管理ツール","id":"554afa850d84e49f5abedbdf"}},"type":"createCard","date":"2015-05-07T05:39:17.530Z","memberCreator":{"id":"53c797959cd0710742a14dce","avatarHash":null,"fullName":"hash rock","initials":"HR","username":"hashrock"}},{"id":"554afa27b04529819be5ce26","idMemberCreator":"53c797959cd0710742a14dce","data":{"list":{"name":"作った","id":"5510ea7a72e8aec6ec62bdac"},"board":{"shortLink":"VusqcRPc","name":"Product","id":"5510ea66af1945352b1c986c"},"card":{"shortLink":"gxIwLfgw","idShort":22,"name":"kanbandown","id":"554af9f2c279fd9fc6f2340e","desc":"Markdownからカンバンに変換するライブラリ\n\nhttps://github.com/hashrock/kanbandown"},"old":{"desc":"https://github.com/hashrock/kanbandown"}},"type":"updateCard","date":"2015-05-07T05:37:43.294Z","memberCreator":{"id":"53c797959cd0710742a14dce","avatarHash":null,"fullName":"hash rock","initials":"HR","username":"hashrock"}},{"id":"554afa132bd688b4b7c1f98a","idMemberCreator":"53c797959cd0710742a14dce","data":{"board":{"shortLink":"VusqcRPc","name":"Product","id":"5510ea66af1945352b1c986c"},"card":{"shortLink":"gxIwLfgw","idShort":22,"name":"kanbandown","id":"554af9f2c279fd9fc6f2340e"},"attachment":{"previewUrl2x":"https://trello-attachments.s3.amazonaws.com/554af9f2c279fd9fc6f2340e/918x525/598b63a03c056e5206a1400905664fe5/f6b25ee6-ec52-11e4-99ea-d074b2b9bcff.gif","previewUrl":"https://trello-attachments.s3.amazonaws.com/554af9f2c279fd9fc6f2340e/600x343/da8b627c556f03d54405d9b8187c5292/f6b25ee6-ec52-11e4-99ea-d074b2b9bcff.gif.png","url":"https://trello-attachments.s3.amazonaws.com/554af9f2c279fd9fc6f2340e/918x525/598b63a03c056e5206a1400905664fe5/f6b25ee6-ec52-11e4-99ea-d074b2b9bcff.gif","name":"f6b25ee6-ec52-11e4-99ea-d074b2b9bcff.gif","id":"554afa122bd688b4b7c1f983"}},"type":"addAttachmentToCard","date":"2015-05-07T05:37:23.621Z","memberCreator":{"id":"53c797959cd0710742a14dce","avatarHash":null,"fullName":"hash rock","initials":"HR","username":"hashrock"}},{"id":"554af9fb674ae6d966cbcf18","idMemberCreator":"53c797959cd0710742a14dce","data":{"list":{"name":"作った","id":"5510ea7a72e8aec6ec62bdac"},"board":{"shortLink":"VusqcRPc","name":"Product","id":"5510ea66af1945352b1c986c"},"card":{"shortLink":"gxIwLfgw","idShort":22,"name":"kanbandown","id":"554af9f2c279fd9fc6f2340e","desc":"https://github.com/hashrock/kanbandown"},"old":{"desc":""}},"type":"updateCard","date":"2015-05-07T05:36:59.747Z","memberCreator":{"id":"53c797959cd0710742a14dce","avatarHash":null,"fullName":"hash rock","initials":"HR","username":"hashrock"}},{"id":"554af9f2c279fd9fc6f2340f","idMemberCreator":"53c797959cd0710742a14dce","data":{"board":{"shortLink":"VusqcRPc","name":"Product","id":"5510ea66af1945352b1c986c"},"list":{"name":"作った","id":"5510ea7a72e8aec6ec62bdac"},"card":{"shortLink":"gxIwLfgw","idShort":22,"name":"kanbandown","id":"554af9f2c279fd9fc6f2340e"}},"type":"createCard","date":"2015-05-07T05:36:50.108Z","memberCreator":{"id":"53c797959cd0710742a14dce","avatarHash":null,"fullName":"hash rock","initials":"HR","username":"hashrock"}},{"id":"554af9b55160310b96d750ab","idMemberCreator":"53c797959cd0710742a14dce","data":{"list":{"name":"作りたい","id":"5510ea73de7581316ca2cad9"},"board":{"shortLink":"VusqcRPc","name":"Product","id":"5510ea66af1945352b1c986c"},"card":{"shortLink":"Jhr5wRzh","idShort":21,"id":"5548c8772f9163a228decda4","name":"ビルドごとに、撮影したgifをアップロードする場所"},"old":{"name":"gifアップロードするツール"}},"type":"updateCard","date":"2015-05-07T05:35:49.051Z","memberCreator":{"id":"53c797959cd0710742a14dce","avatarHash":null,"fullName":"hash rock","initials":"HR","username":"hashrock"}},{"id":"5548c8772f9163a228decda5","idMemberCreator":"53c797959cd0710742a14dce","data":{"board":{"shortLink":"VusqcRPc","name":"Product","id":"5510ea66af1945352b1c986c"},"list":{"name":"作りたい","id":"5510ea73de7581316ca2cad9"},"card":{"shortLink":"Jhr5wRzh","idShort":21,"name":"gifアップロードするツール","id":"5548c8772f9163a228decda4"}},"type":"createCard","date":"2015-05-05T13:41:11.278Z","memberCreator":{"id":"53c797959cd0710742a14dce","avatarHash":null,"fullName":"hash rock","initials":"HR","username":"hashrock"}},{"id":"552ea95f5367a7f97ab32618","idMemberCreator":"53c797959cd0710742a14dce","data":{"listAfter":{"name":"Done","id":"552c7192acf369a608112162"},"listBefore":{"name":"作りたい","id":"5510ea73de7581316ca2cad9"},"board":{"shortLink":"VusqcRPc","name":"Product","id":"5510ea66af1945352b1c986c"},"card":{"shortLink":"tlMcjcld","idShort":15,"name":"JSONのURLを指定すると、いい感じに整形してくれるサイト","id":"5510f16cad10f449d94a44e9","idList":"552c7192acf369a608112162"},"old":{"idList":"5510ea73de7581316ca2cad9"}},"type":"updateCard","date":"2015-04-15T18:09:35.750Z","memberCreator":{"id":"53c797959cd0710742a14dce","avatarHash":null,"fullName":"hash rock","initials":"HR","username":"hashrock"}},{"id":"552ea952aa286b378c60d2e7","idMemberCreator":"53c797959cd0710742a14dce","data":{"list":{"name":"Done","id":"552c7192acf369a608112162"},"board":{"shortLink":"VusqcRPc","name":"Product","id":"5510ea66af1945352b1c986c"},"card":{"shortLink":"ayx8v1po","idShort":16,"name":"Trello API渡すと、JSONで吐いてくれるツール","id":"5510f19583a4b64c44e66e80","pos":32767.5},"old":{"pos":458751}},"type":"updateCard","date":"2015-04-15T18:09:22.587Z","memberCreator":{"id":"53c797959cd0710742a14dce","avatarHash":null,"fullName":"hash rock","initials":"HR","username":"hashrock"}},{"id":"552ea952aa286b378c60d2e6","idMemberCreator":"53c797959cd0710742a14dce","data":{"listAfter":{"name":"Done","id":"552c7192acf369a608112162"},"listBefore":{"name":"作りたい","id":"5510ea73de7581316ca2cad9"},"board":{"shortLink":"VusqcRPc","name":"Product","id":"5510ea66af1945352b1c986c"},"card":{"shortLink":"ayx8v1po","idShort":16,"name":"Trello API渡すと、JSONで吐いてくれるツール","id":"5510f19583a4b64c44e66e80","idList":"552c7192acf369a608112162"},"old":{"idList":"5510ea73de7581316ca2cad9"}},"type":"updateCard","date":"2015-04-15T18:09:22.189Z","memberCreator":{"id":"53c797959cd0710742a14dce","avatarHash":null,"fullName":"hash rock","initials":"HR","username":"hashrock"}},{"id":"552ea938bd803bd810312c48","idMemberCreator":"53c797959cd0710742a14dce","data":{"list":{"name":"作りたい","id":"5510ea73de7581316ca2cad9"},"board":{"shortLink":"VusqcRPc","name":"Product","id":"5510ea66af1945352b1c986c"},"card":{"shortLink":"3yyFQL2t","idShort":20,"name":"２〜３人のチーム向けマネジメントツール","id":"552ea92bfe0c77280b4d3d81","pos":589823},"old":{"pos":524287}},"type":"updateCard","date":"2015-04-15T18:08:56.757Z","memberCreator":{"id":"53c797959cd0710742a14dce","avatarHash":null,"fullName":"hash rock","initials":"HR","username":"hashrock"}},{"id":"552ea938bd803bd810312c47","idMemberCreator":"53c797959cd0710742a14dce","data":{"listAfter":{"name":"作りたい","id":"5510ea73de7581316ca2cad9"},"listBefore":{"name":"ネタ","id":"5510ec6028268c45e167bde6"},"board":{"shortLink":"VusqcRPc","name":"Product","id":"5510ea66af1945352b1c986c"},"card":{"shortLink":"3yyFQL2t","idShort":20,"name":"２〜３人のチーム向けマネジメントツール","id":"552ea92bfe0c77280b4d3d81","idList":"5510ea73de7581316ca2cad9"},"old":{"idList":"5510ec6028268c45e167bde6"}},"type":"updateCard","date":"2015-04-15T18:08:56.693Z","memberCreator":{"id":"53c797959cd0710742a14dce","avatarHash":null,"fullName":"hash rock","initials":"HR","username":"hashrock"}},{"id":"552ea92bfe0c77280b4d3d82","idMemberCreator":"53c797959cd0710742a14dce","data":{"board":{"shortLink":"VusqcRPc","name":"Product","id":"5510ea66af1945352b1c986c"},"list":{"name":"ネタ","id":"5510ec6028268c45e167bde6"},"card":{"shortLink":"3yyFQL2t","idShort":20,"name":"２〜３人のチーム向けマネジメントツール","id":"552ea92bfe0c77280b4d3d81"}},"type":"createCard","date":"2015-04-15T18:08:43.181Z","memberCreator":{"id":"53c797959cd0710742a14dce","avatarHash":null,"fullName":"hash rock","initials":"HR","username":"hashrock"}},{"id":"552c71aeee57099e0824b0eb","idMemberCreator":"53c797959cd0710742a14dce","data":{"list":{"name":"Done","id":"552c7192acf369a608112162"},"board":{"shortLink":"VusqcRPc","name":"Product","id":"5510ea66af1945352b1c986c"},"card":{"shortLink":"XYfGATes","idShort":2,"name":"Trelloからきれいなランディングページ生成ツール","id":"5510eb6f83a4b64c44e66a64"},"text":"とりあえず単品サイト作ってqiitaの記事にした。"},"type":"commentCard","date":"2015-04-14T01:47:26.161Z","memberCreator":{"id":"53c797959cd0710742a14dce","avatarHash":null,"fullName":"hash rock","initials":"HR","username":"hashrock"}},{"id":"552c71955fd635ed7de7ab2a","idMemberCreator":"53c797959cd0710742a14dce","data":{"listAfter":{"name":"Done","id":"552c7192acf369a608112162"},"listBefore":{"name":"作りたい","id":"5510ea73de7581316ca2cad9"},"board":{"shortLink":"VusqcRPc","name":"Product","id":"5510ea66af1945352b1c986c"},"card":{"shortLink":"XYfGATes","idShort":2,"name":"Trelloからきれいなランディングページ生成ツール","id":"5510eb6f83a4b64c44e66a64","idList":"552c7192acf369a608112162"},"old":{"idList":"5510ea73de7581316ca2cad9"}},"type":"updateCard","date":"2015-04-14T01:47:01.433Z","memberCreator":{"id":"53c797959cd0710742a14dce","avatarHash":null,"fullName":"hash rock","initials":"HR","username":"hashrock"}},{"id":"552c7192acf369a608112163","idMemberCreator":"53c797959cd0710742a14dce","data":{"board":{"shortLink":"VusqcRPc","name":"Product","id":"5510ea66af1945352b1c986c"},"list":{"name":"Done","id":"552c7192acf369a608112162"}},"type":"createList","date":"2015-04-14T01:46:58.670Z","memberCreator":{"id":"53c797959cd0710742a14dce","avatarHash":null,"fullName":"hash rock","initials":"HR","username":"hashrock"}},{"id":"551cc779d1ec40ffb62b7ad4","idMemberCreator":"53c797959cd0710742a14dce","data":{"list":{"name":"作った","id":"5510ea7a72e8aec6ec62bdac"},"board":{"shortLink":"VusqcRPc","name":"Product","id":"5510ea66af1945352b1c986c"},"card":{"shortLink":"sMeRPRU3","idShort":19,"name":"sushipm","id":"551ca6e36ab1822cb7820e9e","desc":"npm script検索ツール\n\n[Github](https://github.com/sushicorp/sushipm)"},"old":{"desc":"https://github.com/sushicorp/sushipm"}},"type":"updateCard","date":"2015-04-02T04:37:13.579Z","memberCreator":{"id":"53c797959cd0710742a14dce","avatarHash":null,"fullName":"hash rock","initials":"HR","username":"hashrock"}},{"id":"551cc74318a6c21fa6ea32a6","idMemberCreator":"53c797959cd0710742a14dce","data":{"list":{"name":"作った","id":"5510ea7a72e8aec6ec62bdac"},"board":{"shortLink":"VusqcRPc","name":"Product","id":"5510ea66af1945352b1c986c"},"card":{"shortLink":"sMeRPRU3","idShort":19,"id":"551ca6e36ab1822cb7820e9e","name":"sushipm"},"old":{"name":"npm script便利ツール"}},"type":"updateCard","date":"2015-04-02T04:36:19.957Z","memberCreator":{"id":"53c797959cd0710742a14dce","avatarHash":null,"fullName":"hash rock","initials":"HR","username":"hashrock"}},{"id":"551cc7363dd2dfb0115a24ca","idMemberCreator":"53c797959cd0710742a14dce","data":{"list":{"name":"作った","id":"5510ea7a72e8aec6ec62bdac"},"board":{"shortLink":"VusqcRPc","name":"Product","id":"5510ea66af1945352b1c986c"},"card":{"shortLink":"R7jPrR4c","idShort":1,"name":"taskquest","id":"5510ea8f21854dede6dbcfea","desc":"RPG風カンバンツール\n\n[DEMO](https://github.com/hashrock/taskquest)"},"old":{"desc":"TaskQuest\n\n[DEMO](https://github.com/hashrock/taskquest)"}},"type":"updateCard","date":"2015-04-02T04:36:06.016Z","memberCreator":{"id":"53c797959cd0710742a14dce","avatarHash":null,"fullName":"hash rock","initials":"HR","username":"hashrock"}},{"id":"551cc72a87119ab61037dbc4","idMemberCreator":"53c797959cd0710742a14dce","data":{"list":{"name":"作った","id":"5510ea7a72e8aec6ec62bdac"},"board":{"shortLink":"VusqcRPc","name":"Product","id":"5510ea66af1945352b1c986c"},"card":{"shortLink":"R7jPrR4c","idShort":1,"id":"5510ea8f21854dede6dbcfea","name":"taskquest"},"old":{"name":"RPG風カンバン"}},"type":"updateCard","date":"2015-04-02T04:35:54.168Z","memberCreator":{"id":"53c797959cd0710742a14dce","avatarHash":null,"fullName":"hash rock","initials":"HR","username":"hashrock"}},{"id":"551cc71f962aadab11edc14a","idMemberCreator":"53c797959cd0710742a14dce","data":{"list":{"name":"作った","id":"5510ea7a72e8aec6ec62bdac"},"board":{"shortLink":"VusqcRPc","name":"Product","id":"5510ea66af1945352b1c986c"},"card":{"shortLink":"pRugcuUl","idShort":3,"name":"teamlog","id":"5510ebb8ae3a139d9e67ed4e","desc":"小さなチーム内で情報共有するブログ\n\n[DEMO](https://github.com/hashrock/teamlog)"},"old":{"desc":""}},"type":"updateCard","date":"2015-04-02T04:35:43.270Z","memberCreator":{"id":"53c797959cd0710742a14dce","avatarHash":null,"fullName":"hash rock","initials":"HR","username":"hashrock"}},{"id":"551cc71c771ef70b8a771fcf","idMemberCreator":"53c797959cd0710742a14dce","data":{"list":{"name":"作った","id":"5510ea7a72e8aec6ec62bdac"},"board":{"shortLink":"VusqcRPc","name":"Product","id":"5510ea66af1945352b1c986c"},"card":{"shortLink":"pRugcuUl","idShort":3,"id":"5510ebb8ae3a139d9e67ed4e","name":"teamlog"},"old":{"name":"チームブログ"}},"type":"updateCard","date":"2015-04-02T04:35:40.832Z","memberCreator":{"id":"53c797959cd0710742a14dce","avatarHash":null,"fullName":"hash rock","initials":"HR","username":"hashrock"}},{"id":"551cc646453eba6128c2ad19","idMemberCreator":"53c797959cd0710742a14dce","data":{"list":{"name":"作った","id":"5510ea7a72e8aec6ec62bdac"},"board":{"shortLink":"VusqcRPc","name":"Product","id":"5510ea66af1945352b1c986c"},"card":{"shortLink":"R7jPrR4c","idShort":1,"name":"RPG風カンバン","id":"5510ea8f21854dede6dbcfea","desc":"TaskQuest\n\n[DEMO](https://github.com/hashrock/taskquest)"},"old":{"desc":"https://github.com/hashrock/taskquest"}},"type":"updateCard","date":"2015-04-02T04:32:06.621Z","memberCreator":{"id":"53c797959cd0710742a14dce","avatarHash":null,"fullName":"hash rock","initials":"HR","username":"hashrock"}},{"id":"551ca6fa1ef3afdf103dac45","idMemberCreator":"53c797959cd0710742a14dce","data":{"list":{"name":"作った","id":"5510ea7a72e8aec6ec62bdac"},"board":{"shortLink":"VusqcRPc","name":"Product","id":"5510ea66af1945352b1c986c"},"card":{"shortLink":"sMeRPRU3","idShort":19,"name":"npm script便利ツール","id":"551ca6e36ab1822cb7820e9e","desc":"https://github.com/sushicorp/sushipm"},"old":{"desc":""}},"type":"updateCard","date":"2015-04-02T02:18:34.989Z","memberCreator":{"id":"53c797959cd0710742a14dce","avatarHash":null,"fullName":"hash rock","initials":"HR","username":"hashrock"}},{"id":"551ca6efb94e922c28b30230","idMemberCreator":"53c797959cd0710742a14dce","data":{"board":{"shortLink":"VusqcRPc","name":"Product","id":"5510ea66af1945352b1c986c"},"card":{"shortLink":"sMeRPRU3","idShort":19,"name":"npm script便利ツール","id":"551ca6e36ab1822cb7820e9e"},"attachment":{"previewUrl2x":"https://trello-attachments.s3.amazonaws.com/551ca6e36ab1822cb7820e9e/565x421/5eb0c480bd6cd8dd2d7c0492500366f7/8defc33e-d4b6-11e4-9507-4569c91960be.gif","previewUrl":"https://trello-attachments.s3.amazonaws.com/551ca6e36ab1822cb7820e9e/565x421/5eb0c480bd6cd8dd2d7c0492500366f7/8defc33e-d4b6-11e4-9507-4569c91960be.gif","url":"https://trello-attachments.s3.amazonaws.com/551ca6e36ab1822cb7820e9e/565x421/5eb0c480bd6cd8dd2d7c0492500366f7/8defc33e-d4b6-11e4-9507-4569c91960be.gif","name":"8defc33e-d4b6-11e4-9507-4569c91960be.gif","id":"551ca6edb94e922c28b3022a"}},"type":"addAttachmentToCard","date":"2015-04-02T02:18:23.377Z","memberCreator":{"id":"53c797959cd0710742a14dce","avatarHash":null,"fullName":"hash rock","initials":"HR","username":"hashrock"}},{"id":"551ca6e36ab1822cb7820e9f","idMemberCreator":"53c797959cd0710742a14dce","data":{"board":{"shortLink":"VusqcRPc","name":"Product","id":"5510ea66af1945352b1c986c"},"list":{"name":"作った","id":"5510ea7a72e8aec6ec62bdac"},"card":{"shortLink":"sMeRPRU3","idShort":19,"name":"npm script便利ツール","id":"551ca6e36ab1822cb7820e9e"}},"type":"createCard","date":"2015-04-02T02:18:11.778Z","memberCreator":{"id":"53c797959cd0710742a14dce","avatarHash":null,"fullName":"hash rock","initials":"HR","username":"hashrock"}},{"id":"55123d58b0f1d576464a0448","idMemberCreator":"53c797959cd0710742a14dce","data":{"list":{"name":"作りたい","id":"5510ea73de7581316ca2cad9"},"board":{"shortLink":"VusqcRPc","name":"Product","id":"5510ea66af1945352b1c986c"},"card":{"shortLink":"ZhPysPZq","idShort":18,"name":"ライトウェイトなカンバンツール","id":"55123b647ed28b7bccbba95e"},"text":"taskquestの作り直し的な感じ。ポイントを付加できるようにしたり、日課をつけたりできるようにしたい。"},"type":"commentCard","date":"2015-03-25T04:45:12.623Z","memberCreator":{"id":"53c797959cd0710742a14dce","avatarHash":null,"fullName":"hash rock","initials":"HR","username":"hashrock"}},{"id":"55123b647ed28b7bccbba95f","idMemberCreator":"53c797959cd0710742a14dce","data":{"board":{"shortLink":"VusqcRPc","name":"Product","id":"5510ea66af1945352b1c986c"},"list":{"name":"作りたい","id":"5510ea73de7581316ca2cad9"},"card":{"shortLink":"ZhPysPZq","idShort":18,"name":"ライトウェイトなカンバンツール","id":"55123b647ed28b7bccbba95e"}},"type":"createCard","date":"2015-03-25T04:36:52.932Z","memberCreator":{"id":"53c797959cd0710742a14dce","avatarHash":null,"fullName":"hash rock","initials":"HR","username":"hashrock"}},{"id":"55115447e19606834625fdd6","idMemberCreator":"53c797959cd0710742a14dce","data":{"list":{"name":"作ってる","id":"5510ea77b882b3677c740157"},"board":{"shortLink":"VusqcRPc","name":"Product","id":"5510ea66af1945352b1c986c"},"card":{"shortLink":"rYefpllB","idShort":12,"name":"Text2Gantt","id":"5510eea93d17d51bff963283"},"text":"https://github.com/hashrock/ganttpad"},"type":"commentCard","date":"2015-03-24T12:10:47.391Z","memberCreator":{"id":"53c797959cd0710742a14dce","avatarHash":null,"fullName":"hash rock","initials":"HR","username":"hashrock"}},{"id":"551140702b32963d7765eb57","idMemberCreator":"53c797959cd0710742a14dce","data":{"list":{"name":"作ってる","id":"5510ea77b882b3677c740157"},"board":{"shortLink":"VusqcRPc","name":"Product","id":"5510ea66af1945352b1c986c"},"card":{"shortLink":"rYefpllB","idShort":12,"name":"Text2Gantt","id":"5510eea93d17d51bff963283","desc":"テキストからガントチャートに変換するやつ"},"old":{"desc":""}},"type":"updateCard","date":"2015-03-24T10:46:08.558Z","memberCreator":{"id":"53c797959cd0710742a14dce","avatarHash":null,"fullName":"hash rock","initials":"HR","username":"hashrock"}},{"id":"551140514ab630ecd8b63abf","idMemberCreator":"53c797959cd0710742a14dce","data":{"board":{"shortLink":"VusqcRPc","name":"Product","id":"5510ea66af1945352b1c986c"},"card":{"shortLink":"rYefpllB","idShort":12,"name":"Text2Gantt","id":"5510eea93d17d51bff963283"},"attachment":{"previewUrl2x":"https://trello-attachments.s3.amazonaws.com/5510eea93d17d51bff963283/1000x696/e9e0abbe5d8950b2d9f6b2531ef19566/gantttext.png","previewUrl":"https://trello-attachments.s3.amazonaws.com/5510eea93d17d51bff963283/600x418/d4d1761975d4e3fdd0c6cf4640492101/gantttext.png","url":"https://trello-attachments.s3.amazonaws.com/5510eea93d17d51bff963283/1000x696/e9e0abbe5d8950b2d9f6b2531ef19566/gantttext.png","name":"gantttext.png","id":"5511404f4ab630ecd8b63ab8"}},"type":"addAttachmentToCard","date":"2015-03-24T10:45:37.412Z","memberCreator":{"id":"53c797959cd0710742a14dce","avatarHash":null,"fullName":"hash rock","initials":"HR","username":"hashrock"}},{"id":"5510f31f71a2d428d9dfa6de","idMemberCreator":"53c797959cd0710742a14dce","data":{"board":{"shortLink":"VusqcRPc","name":"Product","id":"5510ea66af1945352b1c986c"},"list":{"name":"ネタ","id":"5510ec6028268c45e167bde6"},"card":{"shortLink":"tRYkXdNs","idShort":17,"name":"Vue.jsのプロジェクトテンプレート吐くツール","id":"5510f31f71a2d428d9dfa6dd"}},"type":"createCard","date":"2015-03-24T05:16:15.827Z","memberCreator":{"id":"53c797959cd0710742a14dce","avatarHash":null,"fullName":"hash rock","initials":"HR","username":"hashrock"}},{"id":"5510f19583a4b64c44e66e81","idMemberCreator":"53c797959cd0710742a14dce","data":{"board":{"shortLink":"VusqcRPc","name":"Product","id":"5510ea66af1945352b1c986c"},"list":{"name":"作りたい","id":"5510ea73de7581316ca2cad9"},"card":{"shortLink":"ayx8v1po","idShort":16,"name":"Trello API渡すと、JSONで吐いてくれるツール","id":"5510f19583a4b64c44e66e80"}},"type":"createCard","date":"2015-03-24T05:09:41.304Z","memberCreator":{"id":"53c797959cd0710742a14dce","avatarHash":null,"fullName":"hash rock","initials":"HR","username":"hashrock"}},{"id":"5510f16cad10f449d94a44ea","idMemberCreator":"53c797959cd0710742a14dce","data":{"board":{"shortLink":"VusqcRPc","name":"Product","id":"5510ea66af1945352b1c986c"},"list":{"name":"作りたい","id":"5510ea73de7581316ca2cad9"},"card":{"shortLink":"tlMcjcld","idShort":15,"name":"JSONのURLを指定すると、いい感じに整形してくれるサイト","id":"5510f16cad10f449d94a44e9"}},"type":"createCard","date":"2015-03-24T05:09:00.871Z","memberCreator":{"id":"53c797959cd0710742a14dce","avatarHash":null,"fullName":"hash rock","initials":"HR","username":"hashrock"}},{"id":"5510f15a0c8bb992906a10be","idMemberCreator":"53c797959cd0710742a14dce","data":{"board":{"shortLink":"VusqcRPc","name":"Product","id":"5510ea66af1945352b1c986c"},"list":{"name":"作りたい","id":"5510ea73de7581316ca2cad9"},"card":{"shortLink":"lLtgXnU7","idShort":14,"name":"HandsonTable編集すると、JSONを公開してくれるサイト","id":"5510f15a0c8bb992906a10bd"}},"type":"createCard","date":"2015-03-24T05:08:42.353Z","memberCreator":{"id":"53c797959cd0710742a14dce","avatarHash":null,"fullName":"hash rock","initials":"HR","username":"hashrock"}},{"id":"5510f1128f20837b9e199914","idMemberCreator":"53c797959cd0710742a14dce","data":{"board":{"shortLink":"VusqcRPc","name":"Product","id":"5510ea66af1945352b1c986c"},"list":{"name":"作りたい","id":"5510ea73de7581316ca2cad9"},"card":{"shortLink":"zizl5aPg","idShort":13,"name":"プロトタイピング向けライブラリ＆サービスのまとめ","id":"5510f1128f20837b9e199913"}},"type":"createCard","date":"2015-03-24T05:07:30.814Z","memberCreator":{"id":"53c797959cd0710742a14dce","avatarHash":null,"fullName":"hash rock","initials":"HR","username":"hashrock"}},{"id":"5510f03ce7814f36e1e0d791","idMemberCreator":"53c797959cd0710742a14dce","data":{"board":{"shortLink":"VusqcRPc","name":"Product","id":"5510ea66af1945352b1c986c"},"list":{"name":"作ってる","id":"5510ea77b882b3677c740157","pos":49151.25},"old":{"pos":16383.75}},"type":"updateList","date":"2015-03-24T05:03:56.493Z","memberCreator":{"id":"53c797959cd0710742a14dce","avatarHash":null,"fullName":"hash rock","initials":"HR","username":"hashrock"}},{"id":"5510f03a56db0041b892143b","idMemberCreator":"53c797959cd0710742a14dce","data":{"board":{"shortLink":"VusqcRPc","name":"Product","id":"5510ea66af1945352b1c986c"},"list":{"name":"作ってる","id":"5510ea77b882b3677c740157","pos":16383.75},"old":{"pos":131071}},"type":"updateList","date":"2015-03-24T05:03:54.962Z","memberCreator":{"id":"53c797959cd0710742a14dce","avatarHash":null,"fullName":"hash rock","initials":"HR","username":"hashrock"}},{"id":"5510f03758539c111883bef2","idMemberCreator":"53c797959cd0710742a14dce","data":{"board":{"shortLink":"VusqcRPc","name":"Product","id":"5510ea66af1945352b1c986c"},"list":{"name":"作った","id":"5510ea7a72e8aec6ec62bdac","pos":32767.5},"old":{"pos":196607}},"type":"updateList","date":"2015-03-24T05:03:51.881Z","memberCreator":{"id":"53c797959cd0710742a14dce","avatarHash":null,"fullName":"hash rock","initials":"HR","username":"hashrock"}},{"id":"5510ef73762a6532d9777a6c","idMemberCreator":"53c797959cd0710742a14dce","data":{"list":{"name":"作りたい","id":"5510ea73de7581316ca2cad9"},"board":{"shortLink":"VusqcRPc","name":"Product","id":"5510ea66af1945352b1c986c"},"card":{"shortLink":"3a5beVlC","idShort":11,"name":"かんたんGIFエディタ","id":"5510eea03d17d51bff96327c"},"text":"Web漫画プラットフォームとして考えたい。"},"type":"commentCard","date":"2015-03-24T05:00:35.222Z","memberCreator":{"id":"53c797959cd0710742a14dce","avatarHash":null,"fullName":"hash rock","initials":"HR","username":"hashrock"}},{"id":"5510ef0d6909f77e44400e22","idMemberCreator":"53c797959cd0710742a14dce","data":{"board":{"shortLink":"VusqcRPc","name":"Product","id":"5510ea66af1945352b1c986c","prefs":{"permissionLevel":"public"}},"old":{"prefs":{"permissionLevel":"private"}}},"type":"updateBoard","date":"2015-03-24T04:58:53.851Z","memberCreator":{"id":"53c797959cd0710742a14dce","avatarHash":null,"fullName":"hash rock","initials":"HR","username":"hashrock"}},{"id":"5510eea93d17d51bff963284","idMemberCreator":"53c797959cd0710742a14dce","data":{"board":{"shortLink":"VusqcRPc","name":"Product","id":"5510ea66af1945352b1c986c"},"list":{"name":"作ってる","id":"5510ea77b882b3677c740157"},"card":{"shortLink":"rYefpllB","idShort":12,"name":"Text2Gantt","id":"5510eea93d17d51bff963283"}},"type":"createCard","date":"2015-03-24T04:57:13.842Z","memberCreator":{"id":"53c797959cd0710742a14dce","avatarHash":null,"fullName":"hash rock","initials":"HR","username":"hashrock"}},{"id":"5510eea03d17d51bff96327d","idMemberCreator":"53c797959cd0710742a14dce","data":{"board":{"shortLink":"VusqcRPc","name":"Product","id":"5510ea66af1945352b1c986c"},"list":{"name":"作りたい","id":"5510ea73de7581316ca2cad9"},"card":{"shortLink":"3a5beVlC","idShort":11,"name":"かんたんGIFエディタ","id":"5510eea03d17d51bff96327c"}},"type":"createCard","date":"2015-03-24T04:57:04.509Z","memberCreator":{"id":"53c797959cd0710742a14dce","avatarHash":null,"fullName":"hash rock","initials":"HR","username":"hashrock"}},{"id":"5510ee56ee3048887cf5faed","idMemberCreator":"53c797959cd0710742a14dce","data":{"board":{"shortLink":"VusqcRPc","name":"Product","id":"5510ea66af1945352b1c986c"},"list":{"name":"作りたい","id":"5510ea73de7581316ca2cad9"},"card":{"shortLink":"5GkuKBzM","idShort":10,"name":"マルチプレイ型RPGツクールみたいなの","id":"5510ee56ee3048887cf5faec"}},"type":"createCard","date":"2015-03-24T04:55:50.535Z","memberCreator":{"id":"53c797959cd0710742a14dce","avatarHash":null,"fullName":"hash rock","initials":"HR","username":"hashrock"}},{"id":"5510ee1a6155825d18045c51","idMemberCreator":"53c797959cd0710742a14dce","data":{"board":{"shortLink":"VusqcRPc","name":"Product","id":"5510ea66af1945352b1c986c"},"card":{"shortLink":"R7jPrR4c","idShort":1,"name":"RPG風カンバン","id":"5510ea8f21854dede6dbcfea"},"attachment":{"previewUrl2x":"https://trello-attachments.s3.amazonaws.com/5510ea8f21854dede6dbcfea/1099x735/a84ce67d604729c8f8d5f298a6cb9112/%E3%82%B9%E3%82%AF%E3%83%AA%E3%83%BC%E3%83%B3%E3%82%B7%E3%83%A7%E3%83%83%E3%83%88_2015-03-24_13.54.29.png","previewUrl":"https://trello-attachments.s3.amazonaws.com/5510ea8f21854dede6dbcfea/600x401/ee2f88eaf47bcbf7a3025a6a6e21e230/%E3%82%B9%E3%82%AF%E3%83%AA%E3%83%BC%E3%83%B3%E3%82%B7%E3%83%A7%E3%83%83%E3%83%88_2015-03-24_13.54.29.png","url":"https://trello-attachments.s3.amazonaws.com/5510ea8f21854dede6dbcfea/1099x735/a84ce67d604729c8f8d5f298a6cb9112/%E3%82%B9%E3%82%AF%E3%83%AA%E3%83%BC%E3%83%B3%E3%82%B7%E3%83%A7%E3%83%83%E3%83%88_2015-03-24_13.54.29.png","name":"スクリーンショット 2015-03-24 13.54.29.png","id":"5510ee186155825d18045c4a"}},"type":"addAttachmentToCard","date":"2015-03-24T04:54:50.251Z","memberCreator":{"id":"53c797959cd0710742a14dce","avatarHash":null,"fullName":"hash rock","initials":"HR","username":"hashrock"}},{"id":"5510ed40a0a95180eccecd80","idMemberCreator":"53c797959cd0710742a14dce","data":{"dateLastEdited":"2015-03-24T04:58:19.356Z","textData":{"emoji":{}},"text":"Redmineの代替として作成。アクティビティグラフなどを装備。","card":{"id":"5510ea8f21854dede6dbcfea","name":"RPG風カンバン","idShort":1,"shortLink":"R7jPrR4c"},"board":{"id":"5510ea66af1945352b1c986c","name":"Product","shortLink":"VusqcRPc"},"list":{"id":"5510ea7a72e8aec6ec62bdac","name":"作った"}},"type":"commentCard","date":"2015-03-24T04:51:12.531Z","memberCreator":{"id":"53c797959cd0710742a14dce","avatarHash":null,"fullName":"hash rock","initials":"HR","username":"hashrock"}},{"id":"5510ecfecea97e4f44eccbb5","idMemberCreator":"53c797959cd0710742a14dce","data":{"board":{"shortLink":"VusqcRPc","name":"Product","id":"5510ea66af1945352b1c986c"},"list":{"name":"ネタ","id":"5510ec6028268c45e167bde6"},"card":{"shortLink":"nQaDEBJ9","idShort":9,"name":"紙ベースワークフローの簡易な代替","id":"5510ecfecea97e4f44eccbb4"}},"type":"createCard","date":"2015-03-24T04:50:06.892Z","memberCreator":{"id":"53c797959cd0710742a14dce","avatarHash":null,"fullName":"hash rock","initials":"HR","username":"hashrock"}},{"id":"5510ecf2bdca3d9e9e3806a4","idMemberCreator":"53c797959cd0710742a14dce","data":{"board":{"shortLink":"VusqcRPc","name":"Product","id":"5510ea66af1945352b1c986c"},"list":{"name":"ネタ","id":"5510ec6028268c45e167bde6"},"card":{"shortLink":"dQu6HGm9","idShort":8,"name":"脳の模倣","id":"5510ecf2bdca3d9e9e3806a3"}},"type":"createCard","date":"2015-03-24T04:49:54.711Z","memberCreator":{"id":"53c797959cd0710742a14dce","avatarHash":null,"fullName":"hash rock","initials":"HR","username":"hashrock"}},{"id":"5510ecc65db284e4fbc21a5f","idMemberCreator":"53c797959cd0710742a14dce","data":{"board":{"shortLink":"VusqcRPc","name":"Product","id":"5510ea66af1945352b1c986c"},"list":{"name":"ネタ","id":"5510ec6028268c45e167bde6"},"card":{"shortLink":"cJxA50lS","idShort":7,"name":"ツールの「かわいさ（モードレス、ミニマル、直接編集）」を大事にしたい","id":"5510ecc65db284e4fbc21a5e"}},"type":"createCard","date":"2015-03-24T04:49:10.886Z","memberCreator":{"id":"53c797959cd0710742a14dce","avatarHash":null,"fullName":"hash rock","initials":"HR","username":"hashrock"}},{"id":"5510ec8a8fa9d9e07126b6d3","idMemberCreator":"53c797959cd0710742a14dce","data":{"board":{"shortLink":"VusqcRPc","name":"Product","id":"5510ea66af1945352b1c986c"},"list":{"name":"ネタ","id":"5510ec6028268c45e167bde6"},"card":{"shortLink":"6gPk0mdY","idShort":6,"name":"既存のツールをモードレスに作り替えたい","id":"5510ec8a8fa9d9e07126b6d2"}},"type":"createCard","date":"2015-03-24T04:48:10.843Z","memberCreator":{"id":"53c797959cd0710742a14dce","avatarHash":null,"fullName":"hash rock","initials":"HR","username":"hashrock"}},{"id":"5510ec77869b8210d9a855ba","idMemberCreator":"53c797959cd0710742a14dce","data":{"board":{"shortLink":"VusqcRPc","name":"Product","id":"5510ea66af1945352b1c986c"},"list":{"name":"ネタ","id":"5510ec6028268c45e167bde6"},"card":{"shortLink":"X1G89hMF","idShort":5,"name":"ドキュメント作成を楽にしたい","id":"5510ec77869b8210d9a855b9"}},"type":"createCard","date":"2015-03-24T04:47:51.495Z","memberCreator":{"id":"53c797959cd0710742a14dce","avatarHash":null,"fullName":"hash rock","initials":"HR","username":"hashrock"}},{"id":"5510ec6e77cfd09044149946","idMemberCreator":"53c797959cd0710742a14dce","data":{"board":{"shortLink":"VusqcRPc","name":"Product","id":"5510ea66af1945352b1c986c"},"list":{"name":"ネタ","id":"5510ec6028268c45e167bde6"},"card":{"shortLink":"Rg5HciTA","idShort":4,"name":"もっとワークフローをゲーミフィケーション化したい","id":"5510ec6e77cfd09044149945"}},"type":"createCard","date":"2015-03-24T04:47:42.555Z","memberCreator":{"id":"53c797959cd0710742a14dce","avatarHash":null,"fullName":"hash rock","initials":"HR","username":"hashrock"}},{"id":"5510ec6028268c45e167bde7","idMemberCreator":"53c797959cd0710742a14dce","data":{"board":{"shortLink":"VusqcRPc","name":"Product","id":"5510ea66af1945352b1c986c"},"list":{"name":"ネタ","id":"5510ec6028268c45e167bde6"}},"type":"createList","date":"2015-03-24T04:47:28.115Z","memberCreator":{"id":"53c797959cd0710742a14dce","avatarHash":null,"fullName":"hash rock","initials":"HR","username":"hashrock"}},{"id":"5510ebe415bbd2d63229ee32","idMemberCreator":"53c797959cd0710742a14dce","data":{"board":{"shortLink":"VusqcRPc","name":"Product","id":"5510ea66af1945352b1c986c"},"card":{"shortLink":"pRugcuUl","idShort":3,"name":"チームブログ","id":"5510ebb8ae3a139d9e67ed4e"},"attachment":{"previewUrl2x":"https://trello-attachments.s3.amazonaws.com/5510ebb8ae3a139d9e67ed4e/794x656/f8cfc36ce39b80d66f8a1e5d5a9a1616/screenshot.png","previewUrl":"https://trello-attachments.s3.amazonaws.com/5510ebb8ae3a139d9e67ed4e/600x496/7f602f33727b9dbec928404e7fddaac9/screenshot.png","url":"https://trello-attachments.s3.amazonaws.com/5510ebb8ae3a139d9e67ed4e/794x656/f8cfc36ce39b80d66f8a1e5d5a9a1616/screenshot.png","name":"screenshot.png","id":"5510ebe215bbd2d63229ee2b"}},"type":"addAttachmentToCard","date":"2015-03-24T04:45:24.305Z","memberCreator":{"id":"53c797959cd0710742a14dce","avatarHash":null,"fullName":"hash rock","initials":"HR","username":"hashrock"}},{"id":"5510ebd582e7ef3de76fdce6","idMemberCreator":"53c797959cd0710742a14dce","data":{"list":{"name":"作った","id":"5510ea7a72e8aec6ec62bdac"},"board":{"shortLink":"VusqcRPc","name":"Product","id":"5510ea66af1945352b1c986c"},"card":{"shortLink":"pRugcuUl","idShort":3,"name":"チームブログ","id":"5510ebb8ae3a139d9e67ed4e"},"text":"https://github.com/hashrock/teamlog"},"type":"commentCard","date":"2015-03-24T04:45:09.948Z","memberCreator":{"id":"53c797959cd0710742a14dce","avatarHash":null,"fullName":"hash rock","initials":"HR","username":"hashrock"}},{"id":"5510ebba651d9d49e744168b","idMemberCreator":"53c797959cd0710742a14dce","data":{"listAfter":{"name":"作った","id":"5510ea7a72e8aec6ec62bdac"},"listBefore":{"name":"作りたい","id":"5510ea73de7581316ca2cad9"},"board":{"shortLink":"VusqcRPc","name":"Product","id":"5510ea66af1945352b1c986c"},"card":{"shortLink":"pRugcuUl","idShort":3,"name":"チームブログ","id":"5510ebb8ae3a139d9e67ed4e","idList":"5510ea7a72e8aec6ec62bdac"},"old":{"idList":"5510ea73de7581316ca2cad9"}},"type":"updateCard","date":"2015-03-24T04:44:42.546Z","memberCreator":{"id":"53c797959cd0710742a14dce","avatarHash":null,"fullName":"hash rock","initials":"HR","username":"hashrock"}},{"id":"5510ebb8ae3a139d9e67ed4f","idMemberCreator":"53c797959cd0710742a14dce","data":{"board":{"shortLink":"VusqcRPc","name":"Product","id":"5510ea66af1945352b1c986c"},"list":{"name":"作りたい","id":"5510ea73de7581316ca2cad9"},"card":{"shortLink":"pRugcuUl","idShort":3,"name":"チームブログ","id":"5510ebb8ae3a139d9e67ed4e"}},"type":"createCard","date":"2015-03-24T04:44:40.190Z","memberCreator":{"id":"53c797959cd0710742a14dce","avatarHash":null,"fullName":"hash rock","initials":"HR","username":"hashrock"}},{"id":"5510eb7b7b4c8141b8355a85","idMemberCreator":"53c797959cd0710742a14dce","data":{"list":{"name":"作りたい","id":"5510ea73de7581316ca2cad9"},"board":{"shortLink":"VusqcRPc","name":"Product","id":"5510ea66af1945352b1c986c"},"card":{"shortLink":"XYfGATes","idShort":2,"id":"5510eb6f83a4b64c44e66a64","name":"Trelloからきれいなランディングページ生成ツール"},"old":{"name":"Trelloからきれいなランディングページ生成"}},"type":"updateCard","date":"2015-03-24T04:43:39.355Z","memberCreator":{"id":"53c797959cd0710742a14dce","avatarHash":null,"fullName":"hash rock","initials":"HR","username":"hashrock"}},{"id":"5510eb6f83a4b64c44e66a65","idMemberCreator":"53c797959cd0710742a14dce","data":{"board":{"shortLink":"VusqcRPc","name":"Product","id":"5510ea66af1945352b1c986c"},"list":{"name":"作りたい","id":"5510ea73de7581316ca2cad9"},"card":{"shortLink":"XYfGATes","idShort":2,"name":"Trelloからきれいなランディングページ生成","id":"5510eb6f83a4b64c44e66a64"}},"type":"createCard","date":"2015-03-24T04:43:27.481Z","memberCreator":{"id":"53c797959cd0710742a14dce","avatarHash":null,"fullName":"hash rock","initials":"HR","username":"hashrock"}},{"id":"5510eb546d608f796c94e059","idMemberCreator":"53c797959cd0710742a14dce","data":{"list":{"name":"作った","id":"5510ea7a72e8aec6ec62bdac"},"board":{"shortLink":"VusqcRPc","name":"Product","id":"5510ea66af1945352b1c986c"},"card":{"shortLink":"R7jPrR4c","idShort":1,"id":"5510ea8f21854dede6dbcfea","name":"RPG風カンバン"},"old":{"name":"ゲーム風カンバン"}},"type":"updateCard","date":"2015-03-24T04:43:00.055Z","memberCreator":{"id":"53c797959cd0710742a14dce","avatarHash":null,"fullName":"hash rock","initials":"HR","username":"hashrock"}},{"id":"5510eb4a92d1eadd08240a16","idMemberCreator":"53c797959cd0710742a14dce","data":{"list":{"name":"作った","id":"5510ea7a72e8aec6ec62bdac"},"board":{"shortLink":"VusqcRPc","name":"Product","id":"5510ea66af1945352b1c986c"},"card":{"shortLink":"R7jPrR4c","idShort":1,"id":"5510ea8f21854dede6dbcfea","name":"ゲーム風カンバン"},"old":{"name":"TaskQuest"}},"type":"updateCard","date":"2015-03-24T04:42:50.324Z","memberCreator":{"id":"53c797959cd0710742a14dce","avatarHash":null,"fullName":"hash rock","initials":"HR","username":"hashrock"}},{"id":"5510eaab3515661b7c887f21","idMemberCreator":"53c797959cd0710742a14dce","data":{"list":{"name":"作った","id":"5510ea7a72e8aec6ec62bdac"},"board":{"shortLink":"VusqcRPc","name":"Product","id":"5510ea66af1945352b1c986c"},"card":{"shortLink":"R7jPrR4c","idShort":1,"name":"TaskQuest","id":"5510ea8f21854dede6dbcfea","desc":"https://github.com/hashrock/taskquest"},"old":{"desc":""}},"type":"updateCard","date":"2015-03-24T04:40:11.780Z","memberCreator":{"id":"53c797959cd0710742a14dce","avatarHash":null,"fullName":"hash rock","initials":"HR","username":"hashrock"}},{"id":"5510ea8f21854dede6dbcfeb","idMemberCreator":"53c797959cd0710742a14dce","data":{"board":{"shortLink":"VusqcRPc","name":"Product","id":"5510ea66af1945352b1c986c"},"list":{"name":"作った","id":"5510ea7a72e8aec6ec62bdac"},"card":{"shortLink":"R7jPrR4c","idShort":1,"name":"TaskQuest","id":"5510ea8f21854dede6dbcfea"}},"type":"createCard","date":"2015-03-24T04:39:43.764Z","memberCreator":{"id":"53c797959cd0710742a14dce","avatarHash":null,"fullName":"hash rock","initials":"HR","username":"hashrock"}},{"id":"5510ea7a72e8aec6ec62bdad","idMemberCreator":"53c797959cd0710742a14dce","data":{"board":{"shortLink":"VusqcRPc","name":"Product","id":"5510ea66af1945352b1c986c"},"list":{"name":"作った","id":"5510ea7a72e8aec6ec62bdac"}},"type":"createList","date":"2015-03-24T04:39:22.170Z","memberCreator":{"id":"53c797959cd0710742a14dce","avatarHash":null,"fullName":"hash rock","initials":"HR","username":"hashrock"}},{"id":"5510ea77b882b3677c740158","idMemberCreator":"53c797959cd0710742a14dce","data":{"board":{"shortLink":"VusqcRPc","name":"Product","id":"5510ea66af1945352b1c986c"},"list":{"name":"作ってる","id":"5510ea77b882b3677c740157"}},"type":"createList","date":"2015-03-24T04:39:19.719Z","memberCreator":{"id":"53c797959cd0710742a14dce","avatarHash":null,"fullName":"hash rock","initials":"HR","username":"hashrock"}},{"id":"5510ea73de7581316ca2cada","idMemberCreator":"53c797959cd0710742a14dce","data":{"board":{"shortLink":"VusqcRPc","name":"Product","id":"5510ea66af1945352b1c986c"},"list":{"name":"作りたい","id":"5510ea73de7581316ca2cad9"}},"type":"createList","date":"2015-03-24T04:39:15.929Z","memberCreator":{"id":"53c797959cd0710742a14dce","avatarHash":null,"fullName":"hash rock","initials":"HR","username":"hashrock"}},{"id":"5510ea66af1945352b1c986e","idMemberCreator":"53c797959cd0710742a14dce","data":{"board":{"shortLink":"VusqcRPc","name":"Product","id":"5510ea66af1945352b1c986c"}},"type":"createBoard","date":"2015-03-24T04:39:02.463Z","memberCreator":{"id":"53c797959cd0710742a14dce","avatarHash":null,"fullName":"hash rock","initials":"HR","username":"hashrock"}}]}